{
"meta":{"test_sets":[],"test_metrics":[],"learn_metrics":[{"best_value":"Min","name":"MultiClass"}],"launch_mode":"Train","parameters":"","iteration_count":1000,"learn_sets":["learn"],"name":"experiment"},
"iterations":[
{"learn":[1.268997638],"iteration":0,"passed_time":0.163713836,"remaining_time":163.5501221},
{"learn":[1.179290308],"iteration":1,"passed_time":0.3263989226,"remaining_time":162.8730624},
{"learn":[1.110303657],"iteration":2,"passed_time":0.5217831974,"remaining_time":173.4059493},
{"learn":[1.051738362],"iteration":3,"passed_time":0.6781788233,"remaining_time":168.866527},
{"learn":[1.000953944],"iteration":4,"passed_time":0.8699037351,"remaining_time":173.1108433},
{"learn":[0.9616385962],"iteration":5,"passed_time":1.107494641,"remaining_time":183.4749455},
{"learn":[0.9251868325],"iteration":6,"passed_time":1.313105777,"remaining_time":186.2734337},
{"learn":[0.8924414516],"iteration":7,"passed_time":1.517229449,"remaining_time":188.1364517},
{"learn":[0.8660463946],"iteration":8,"passed_time":1.737004908,"remaining_time":191.2635405},
{"learn":[0.8401908345],"iteration":9,"passed_time":1.956848267,"remaining_time":193.7279784},
{"learn":[0.8175299265],"iteration":10,"passed_time":2.11322536,"remaining_time":189.998171},
{"learn":[0.8003747273],"iteration":11,"passed_time":2.312599651,"remaining_time":190.404038},
{"learn":[0.7822348899],"iteration":12,"passed_time":2.524356965,"remaining_time":191.6569481},
{"learn":[0.7679373378],"iteration":13,"passed_time":2.700924169,"remaining_time":190.2222308},
{"learn":[0.7534662455],"iteration":14,"passed_time":2.911905636,"remaining_time":191.2151368},
{"learn":[0.73912904],"iteration":15,"passed_time":3.109244004,"remaining_time":191.2185063},
{"learn":[0.7288450736],"iteration":16,"passed_time":3.29671913,"remaining_time":190.6279356},
{"learn":[0.7183756668],"iteration":17,"passed_time":3.455619028,"remaining_time":188.5232159},
{"learn":[0.7061087868],"iteration":18,"passed_time":3.637611605,"remaining_time":187.8156308},
{"learn":[0.6976961756],"iteration":19,"passed_time":3.829804073,"remaining_time":187.6603996},
{"learn":[0.6883375331],"iteration":20,"passed_time":4.022681864,"remaining_time":187.5335974},
{"learn":[0.6807704164],"iteration":21,"passed_time":4.209345723,"remaining_time":187.1245508},
{"learn":[0.6719500736],"iteration":22,"passed_time":4.404208726,"remaining_time":187.0831272},
{"learn":[0.665350725],"iteration":23,"passed_time":4.594075757,"remaining_time":186.8257475},
{"learn":[0.659092374],"iteration":24,"passed_time":4.764557753,"remaining_time":185.8177524},
{"learn":[0.6550406503],"iteration":25,"passed_time":4.909528385,"remaining_time":183.9184864},
{"learn":[0.6470113091],"iteration":26,"passed_time":5.094388254,"remaining_time":183.5866582},
{"learn":[0.6417603647],"iteration":27,"passed_time":5.280509643,"remaining_time":183.3091205},
{"learn":[0.6363398829],"iteration":28,"passed_time":5.476549112,"remaining_time":183.369972},
{"learn":[0.6322438317],"iteration":29,"passed_time":5.704605654,"remaining_time":184.4489162},
{"learn":[0.6284372583],"iteration":30,"passed_time":5.895860725,"remaining_time":184.2931949},
{"learn":[0.6254802061],"iteration":31,"passed_time":6.11725036,"remaining_time":185.0468234},
{"learn":[0.6206857554],"iteration":32,"passed_time":6.26479314,"remaining_time":183.5774232},
{"learn":[0.6184023906],"iteration":33,"passed_time":6.437561571,"remaining_time":182.9024846},
{"learn":[0.6147433776],"iteration":34,"passed_time":6.630972024,"remaining_time":182.8253715},
{"learn":[0.6106902796],"iteration":35,"passed_time":6.787937912,"remaining_time":181.765893},
{"learn":[0.6083158742],"iteration":36,"passed_time":6.969440349,"remaining_time":181.3938123},
{"learn":[0.6051266131],"iteration":37,"passed_time":7.164819327,"remaining_time":181.3830577},
{"learn":[0.6015597465],"iteration":38,"passed_time":7.355897,"remaining_time":181.2568466},
{"learn":[0.5984403788],"iteration":39,"passed_time":7.557875596,"remaining_time":181.3890143},
{"learn":[0.5956405892],"iteration":40,"passed_time":7.720808226,"remaining_time":180.5915875},
{"learn":[0.5943206106],"iteration":41,"passed_time":7.899546769,"remaining_time":180.1849001},
{"learn":[0.5922313971],"iteration":42,"passed_time":8.087223772,"remaining_time":179.9877477},
{"learn":[0.5909024973],"iteration":43,"passed_time":8.278042939,"remaining_time":179.8592966},
{"learn":[0.5884386312],"iteration":44,"passed_time":8.488127163,"remaining_time":180.1369209},
{"learn":[0.5855539041],"iteration":45,"passed_time":8.687943566,"remaining_time":180.1803948},
{"learn":[0.5836399425],"iteration":46,"passed_time":8.884557567,"remaining_time":180.1485822},
{"learn":[0.5816328255],"iteration":47,"passed_time":9.0972099,"remaining_time":180.4279964},
{"learn":[0.5807868272],"iteration":48,"passed_time":9.263084108,"remaining_time":179.7794487},
{"learn":[0.579636392],"iteration":49,"passed_time":9.408094899,"remaining_time":178.7538031},
{"learn":[0.5773739672],"iteration":50,"passed_time":9.600164101,"remaining_time":178.6383477},
{"learn":[0.5750988217],"iteration":51,"passed_time":9.790169296,"remaining_time":178.4823172},
{"learn":[0.5734510947],"iteration":52,"passed_time":9.983815169,"remaining_time":178.390056},
{"learn":[0.5715720816],"iteration":53,"passed_time":10.19240266,"remaining_time":178.5557948},
{"learn":[0.5684395276],"iteration":54,"passed_time":10.37210884,"remaining_time":178.2116883},
{"learn":[0.567109061],"iteration":55,"passed_time":10.54996795,"remaining_time":177.8423169},
{"learn":[0.5655573475],"iteration":56,"passed_time":10.70593716,"remaining_time":177.1175217},
{"learn":[0.5642829108],"iteration":57,"passed_time":10.87644768,"remaining_time":176.6485123},
{"learn":[0.5629660545],"iteration":58,"passed_time":11.06389835,"remaining_time":176.4598024},
{"learn":[0.5603563],"iteration":59,"passed_time":11.25372235,"remaining_time":176.3083169},
{"learn":[0.559441743],"iteration":60,"passed_time":11.4480562,"remaining_time":176.2249962},
{"learn":[0.5578862152],"iteration":61,"passed_time":11.62637709,"remaining_time":175.895834},
{"learn":[0.5568488129],"iteration":62,"passed_time":11.81751767,"remaining_time":175.7621279},
{"learn":[0.5551096628],"iteration":63,"passed_time":12.0258103,"remaining_time":175.8774756},
{"learn":[0.5540528967],"iteration":64,"passed_time":12.19928873,"remaining_time":175.4820763},
{"learn":[0.5532749996],"iteration":65,"passed_time":12.37371901,"remaining_time":175.1068721},
{"learn":[0.5516109538],"iteration":66,"passed_time":12.55311213,"remaining_time":174.8067705},
{"learn":[0.5505443993],"iteration":67,"passed_time":12.71286895,"remaining_time":174.2410862},
{"learn":[0.5484714801],"iteration":68,"passed_time":12.88772694,"remaining_time":173.8909244},
{"learn":[0.5475750952],"iteration":69,"passed_time":13.08850074,"remaining_time":173.8900812},
{"learn":[0.546258719],"iteration":70,"passed_time":13.29431074,"remaining_time":173.9495025},
{"learn":[0.5445333665],"iteration":71,"passed_time":13.48569665,"remaining_time":173.8156457},
{"learn":[0.543594565],"iteration":72,"passed_time":13.62960978,"remaining_time":173.0773736},
{"learn":[0.5422163352],"iteration":73,"passed_time":13.79766885,"remaining_time":172.6573157},
{"learn":[0.5402044578],"iteration":74,"passed_time":13.9713206,"remaining_time":172.3129541},
{"learn":[0.5394815071],"iteration":75,"passed_time":14.18023799,"remaining_time":172.4018408},
{"learn":[0.5384974711],"iteration":76,"passed_time":14.38502646,"remaining_time":172.433499},
{"learn":[0.5376361381],"iteration":77,"passed_time":14.58349962,"remaining_time":172.3844443},
{"learn":[0.5367862917],"iteration":78,"passed_time":14.79788166,"remaining_time":172.5170761},
{"learn":[0.5357992154],"iteration":79,"passed_time":14.97419682,"remaining_time":172.2032634},
{"learn":[0.5345101263],"iteration":80,"passed_time":15.12884355,"remaining_time":171.6470028},
{"learn":[0.5332526385],"iteration":81,"passed_time":15.31983299,"remaining_time":171.5073986},
{"learn":[0.532870668],"iteration":82,"passed_time":15.51544763,"remaining_time":171.4176563},
{"learn":[0.5321407669],"iteration":83,"passed_time":15.72161962,"remaining_time":171.4405188},
{"learn":[0.5309699391],"iteration":84,"passed_time":15.9228613,"remaining_time":171.4049186},
{"learn":[0.5300374128],"iteration":85,"passed_time":16.12031219,"remaining_time":171.3251784},
{"learn":[0.5294300658],"iteration":86,"passed_time":16.28097196,"remaining_time":170.8566367},
{"learn":[0.5287715908],"iteration":87,"passed_time":16.43816019,"remaining_time":170.3591147},
{"learn":[0.5280038515],"iteration":88,"passed_time":16.60037185,"remaining_time":169.9206601},
{"learn":[0.5267538451],"iteration":89,"passed_time":16.8159211,"remaining_time":170.0276467},
{"learn":[0.5256338973],"iteration":90,"passed_time":16.97748031,"remaining_time":169.5882374},
{"learn":[0.5247906516],"iteration":91,"passed_time":17.16471791,"remaining_time":169.4083028},
{"learn":[0.5233930229],"iteration":92,"passed_time":17.37199574,"remaining_time":169.4236574},
{"learn":[0.5224197153],"iteration":93,"passed_time":17.56284582,"remaining_time":169.2759395},
{"learn":[0.5216126943],"iteration":94,"passed_time":17.74007968,"remaining_time":168.9976012},
{"learn":[0.5200985598],"iteration":95,"passed_time":17.90792707,"remaining_time":168.6329799},
{"learn":[0.5189863956],"iteration":96,"passed_time":18.11771438,"remaining_time":168.6628462},
{"learn":[0.5181048099],"iteration":97,"passed_time":18.30601297,"remaining_time":168.4900378},
{"learn":[0.5173348573],"iteration":98,"passed_time":18.50831736,"remaining_time":168.4443832},
{"learn":[0.5163024507],"iteration":99,"passed_time":18.71319215,"remaining_time":168.4187294},
{"learn":[0.5153820326],"iteration":100,"passed_time":18.93428645,"remaining_time":168.5338962},
{"learn":[0.5144126617],"iteration":101,"passed_time":19.13471695,"remaining_time":168.4605473},
{"learn":[0.5136440967],"iteration":102,"passed_time":19.28448682,"remaining_time":167.9435406},
{"learn":[0.5129816493],"iteration":103,"passed_time":19.43956416,"remaining_time":167.479322},
{"learn":[0.5115203694],"iteration":104,"passed_time":19.64472238,"remaining_time":167.4478717},
{"learn":[0.5106862409],"iteration":105,"passed_time":19.83547129,"remaining_time":167.2916164},
{"learn":[0.5090958533],"iteration":106,"passed_time":20.03279952,"remaining_time":167.1896259},
{"learn":[0.5081822595],"iteration":107,"passed_time":20.23870134,"remaining_time":167.1566814},
{"learn":[0.5073294049],"iteration":108,"passed_time":20.44054741,"remaining_time":167.0874105},
{"learn":[0.505960328],"iteration":109,"passed_time":20.598997,"remaining_time":166.6646121},
{"learn":[0.5052904266],"iteration":110,"passed_time":20.74588671,"remaining_time":166.1539935},
{"learn":[0.504227137],"iteration":111,"passed_time":20.95033394,"remaining_time":166.1062191},
{"learn":[0.5035902288],"iteration":112,"passed_time":21.15370707,"remaining_time":166.0472405},
{"learn":[0.5029175379],"iteration":113,"passed_time":21.35270449,"remaining_time":165.9517208},
{"learn":[0.5023904759],"iteration":114,"passed_time":21.56094311,"remaining_time":165.9255187},
{"learn":[0.5011830621],"iteration":115,"passed_time":21.77156136,"remaining_time":165.9143124},
{"learn":[0.5001205266],"iteration":116,"passed_time":21.95941774,"remaining_time":165.7279133},
{"learn":[0.4991610039],"iteration":117,"passed_time":22.13963569,"remaining_time":165.4843956},
{"learn":[0.4980116024],"iteration":118,"passed_time":22.30426708,"remaining_time":165.1265487},
{"learn":[0.4972138344],"iteration":119,"passed_time":22.49996842,"remaining_time":164.9997684},
{"learn":[0.4963421097],"iteration":120,"passed_time":22.69876417,"remaining_time":164.8943281},
{"learn":[0.495293463],"iteration":121,"passed_time":22.8780131,"remaining_time":164.6466844},
{"learn":[0.4940121213],"iteration":122,"passed_time":23.0951419,"remaining_time":164.6702394},
{"learn":[0.4930389582],"iteration":123,"passed_time":23.30569409,"remaining_time":164.6434518},
{"learn":[0.4921586451],"iteration":124,"passed_time":23.52124231,"remaining_time":164.6486962},
{"learn":[0.4915328141],"iteration":125,"passed_time":23.65988223,"remaining_time":164.1169609},
{"learn":[0.4908344847],"iteration":126,"passed_time":23.8514234,"remaining_time":163.95506},
{"learn":[0.4901159869],"iteration":127,"passed_time":24.02400573,"remaining_time":163.663539},
{"learn":[0.4893003642],"iteration":128,"passed_time":24.23680679,"remaining_time":163.6454164},
{"learn":[0.4883053971],"iteration":129,"passed_time":24.42356575,"remaining_time":163.4500169},
{"learn":[0.4876778927],"iteration":130,"passed_time":24.61396633,"remaining_time":163.2789064},
{"learn":[0.4869207799],"iteration":131,"passed_time":24.81302751,"remaining_time":163.1644536},
{"learn":[0.4866264725],"iteration":132,"passed_time":25.02419269,"remaining_time":163.127632},
{"learn":[0.485729872],"iteration":133,"passed_time":25.2281988,"remaining_time":163.0419415},
{"learn":[0.4853113761],"iteration":134,"passed_time":25.43714603,"remaining_time":162.9861579},
{"learn":[0.4847138166],"iteration":135,"passed_time":25.64783753,"remaining_time":162.9392031},
{"learn":[0.4836600892],"iteration":136,"passed_time":25.84409434,"remaining_time":162.79893},
{"learn":[0.4825354689],"iteration":137,"passed_time":26.0265045,"remaining_time":162.5713542},
{"learn":[0.4814897698],"iteration":138,"passed_time":26.22909221,"remaining_time":162.4694129},
{"learn":[0.4805687153],"iteration":139,"passed_time":26.43508643,"remaining_time":162.3869595},
{"learn":[0.4794041784],"iteration":140,"passed_time":26.61783284,"remaining_time":162.1611235},
{"learn":[0.4783884798],"iteration":141,"passed_time":26.81330958,"remaining_time":162.0128142},
{"learn":[0.4777731979],"iteration":142,"passed_time":27.02614996,"remaining_time":161.9679057},
{"learn":[0.4771166071],"iteration":143,"passed_time":27.21458072,"remaining_time":161.7755631},
{"learn":[0.4760876964],"iteration":144,"passed_time":27.36424237,"remaining_time":161.3546705},
{"learn":[0.4755894205],"iteration":145,"passed_time":27.5553786,"remaining_time":161.1800913},
{"learn":[0.4747483318],"iteration":146,"passed_time":27.77373367,"remaining_time":161.1632301},
{"learn":[0.4742132556],"iteration":147,"passed_time":27.9562125,"remaining_time":160.9371152},
{"learn":[0.4733519652],"iteration":148,"passed_time":28.12212649,"remaining_time":160.6169775},
{"learn":[0.4720802812],"iteration":149,"passed_time":28.32559582,"remaining_time":160.5117096},
{"learn":[0.471445115],"iteration":150,"passed_time":28.48668639,"remaining_time":160.1668659},
{"learn":[0.4708782968],"iteration":151,"passed_time":28.67246287,"remaining_time":159.9621613},
{"learn":[0.4703765399],"iteration":152,"passed_time":28.88235291,"remaining_time":159.8911955},
{"learn":[0.4694360804],"iteration":153,"passed_time":29.11091605,"remaining_time":159.9210064},
{"learn":[0.4687448951],"iteration":154,"passed_time":29.26399144,"remaining_time":159.5359533},
{"learn":[0.4675156561],"iteration":155,"passed_time":29.45180197,"remaining_time":159.3418004},
{"learn":[0.4669027191],"iteration":156,"passed_time":29.64815415,"remaining_time":159.193592},
{"learn":[0.4660168492],"iteration":157,"passed_time":29.83739037,"remaining_time":159.0068525},
{"learn":[0.465125618],"iteration":158,"passed_time":30.04278146,"remaining_time":158.9055296},
{"learn":[0.4643299415],"iteration":159,"passed_time":30.24482314,"remaining_time":158.7853215},
{"learn":[0.4638824762],"iteration":160,"passed_time":30.47144861,"remaining_time":158.7922073},
{"learn":[0.4633592192],"iteration":161,"passed_time":30.64983512,"remaining_time":158.546678},
{"learn":[0.4627415668],"iteration":162,"passed_time":30.78624691,"remaining_time":158.0864335},
{"learn":[0.4621081777],"iteration":163,"passed_time":30.95960742,"remaining_time":157.8184866},
{"learn":[0.4612918634],"iteration":164,"passed_time":31.14486327,"remaining_time":157.6118838},
{"learn":[0.4607849104],"iteration":165,"passed_time":31.34110478,"remaining_time":157.4607312},
{"learn":[0.4601340648],"iteration":166,"passed_time":31.53569389,"remaining_time":157.3007965},
{"learn":[0.459456052],"iteration":167,"passed_time":31.74991094,"remaining_time":157.2376542},
{"learn":[0.4588854684],"iteration":168,"passed_time":31.90956385,"remaining_time":156.9044235},
{"learn":[0.4579376965],"iteration":169,"passed_time":32.04987442,"remaining_time":156.4787986},
{"learn":[0.4573593098],"iteration":170,"passed_time":32.18946216,"remaining_time":156.0530066},
{"learn":[0.4567936396],"iteration":171,"passed_time":32.36234817,"remaining_time":155.7908389},
{"learn":[0.4561188906],"iteration":172,"passed_time":32.50818222,"remaining_time":155.4003855},
{"learn":[0.4555592787],"iteration":173,"passed_time":32.66264054,"remaining_time":155.0536844},
{"learn":[0.4544801071],"iteration":174,"passed_time":32.80225078,"remaining_time":154.6391822},
{"learn":[0.4540534303],"iteration":175,"passed_time":32.93377366,"remaining_time":154.1899403},
{"learn":[0.4535737265],"iteration":176,"passed_time":33.07853354,"remaining_time":153.8058368},
{"learn":[0.4528437145],"iteration":177,"passed_time":33.22470458,"remaining_time":153.4309391},
{"learn":[0.4522930689],"iteration":178,"passed_time":33.35592135,"remaining_time":152.990008},
{"learn":[0.4518342733],"iteration":179,"passed_time":33.48782355,"remaining_time":152.5556406},
{"learn":[0.4513771745],"iteration":180,"passed_time":33.61438649,"remaining_time":152.100456},
{"learn":[0.4504253663],"iteration":181,"passed_time":33.75790877,"remaining_time":151.7251064},
{"learn":[0.4498313009],"iteration":182,"passed_time":33.8850795,"remaining_time":151.2792894},
{"learn":[0.4492525253],"iteration":183,"passed_time":34.01422538,"remaining_time":150.8456952},
{"learn":[0.4484880082],"iteration":184,"passed_time":34.15175477,"remaining_time":150.4523251},
{"learn":[0.4477512648],"iteration":185,"passed_time":34.2792524,"remaining_time":150.0178035},
{"learn":[0.4474609975],"iteration":186,"passed_time":34.41793935,"remaining_time":149.6352123},
{"learn":[0.4469737257],"iteration":187,"passed_time":34.54641441,"remaining_time":149.211109},
{"learn":[0.4461012043],"iteration":188,"passed_time":34.68911703,"remaining_time":148.8511847},
{"learn":[0.4453893488],"iteration":189,"passed_time":34.83210569,"remaining_time":148.4947664},
{"learn":[0.4448219808],"iteration":190,"passed_time":35.02604674,"remaining_time":148.3563969},
{"learn":[0.4443566705],"iteration":191,"passed_time":35.22417402,"remaining_time":148.2350656},
{"learn":[0.4435473701],"iteration":192,"passed_time":35.43310924,"remaining_time":148.1581303},
{"learn":[0.4432129128],"iteration":193,"passed_time":35.62644875,"remaining_time":148.0150397},
{"learn":[0.4426912911],"iteration":194,"passed_time":35.83310292,"remaining_time":147.9263992},
{"learn":[0.4420555222],"iteration":195,"passed_time":36.03039482,"remaining_time":147.7981502},
{"learn":[0.4408182869],"iteration":196,"passed_time":36.19395499,"remaining_time":147.5317049},
{"learn":[0.4403041458],"iteration":197,"passed_time":36.3730273,"remaining_time":147.3291308},
{"learn":[0.4398361206],"iteration":198,"passed_time":36.56410019,"remaining_time":147.1750968},
{"learn":[0.4391889499],"iteration":199,"passed_time":36.74116126,"remaining_time":146.9646451},
{"learn":[0.43858646],"iteration":200,"passed_time":36.90228149,"remaining_time":146.6911588},
{"learn":[0.4382360761],"iteration":201,"passed_time":37.04421279,"remaining_time":146.3429792},
{"learn":[0.4378179044],"iteration":202,"passed_time":37.22394501,"remaining_time":146.1452422},
{"learn":[0.4369041703],"iteration":203,"passed_time":37.37478227,"remaining_time":145.8349347},
{"learn":[0.436420869],"iteration":204,"passed_time":37.52427974,"remaining_time":145.5209873},
{"learn":[0.4360611893],"iteration":205,"passed_time":37.65295175,"remaining_time":145.1283674},
{"learn":[0.435305985],"iteration":206,"passed_time":37.79741935,"remaining_time":144.7988094},
{"learn":[0.4347677033],"iteration":207,"passed_time":37.96867124,"remaining_time":144.5730174},
{"learn":[0.4343817099],"iteration":208,"passed_time":38.11150015,"remaining_time":144.2401752},
{"learn":[0.4336494062],"iteration":209,"passed_time":38.27495637,"remaining_time":143.9867406},
{"learn":[0.4329800712],"iteration":210,"passed_time":38.44744126,"remaining_time":143.7679202},
{"learn":[0.4322001786],"iteration":211,"passed_time":38.59948907,"remaining_time":143.4735726},
{"learn":[0.4314475255],"iteration":212,"passed_time":38.77298756,"remaining_time":143.2598179},
{"learn":[0.4309909406],"iteration":213,"passed_time":38.91570499,"remaining_time":142.9333838},
{"learn":[0.4306103013],"iteration":214,"passed_time":39.04710264,"remaining_time":142.5673282},
{"learn":[0.4298664231],"iteration":215,"passed_time":39.21724508,"remaining_time":142.3440747},
{"learn":[0.4293124421],"iteration":216,"passed_time":39.37578201,"remaining_time":142.0794346},
{"learn":[0.4289638131],"iteration":217,"passed_time":39.54448487,"remaining_time":141.8522347},
{"learn":[0.4283386335],"iteration":218,"passed_time":39.70089993,"remaining_time":141.5817482},
{"learn":[0.4278429887],"iteration":219,"passed_time":39.85471632,"remaining_time":141.3030851},
{"learn":[0.4272958798],"iteration":220,"passed_time":40.02334246,"remaining_time":141.0777547},
{"learn":[0.426775869],"iteration":221,"passed_time":40.16188857,"remaining_time":140.7475194},
{"learn":[0.4261071495],"iteration":222,"passed_time":40.28938672,"remaining_time":140.3805089},
{"learn":[0.4258378018],"iteration":223,"passed_time":40.42896627,"remaining_time":140.0574903},
{"learn":[0.4252152859],"iteration":224,"passed_time":40.5915393,"remaining_time":139.815302},
{"learn":[0.424588805],"iteration":225,"passed_time":40.73692209,"remaining_time":139.5149456},
{"learn":[0.4242586772],"iteration":226,"passed_time":40.9027049,"remaining_time":139.2854224},
{"learn":[0.4236032774],"iteration":227,"passed_time":41.07583898,"remaining_time":139.0813495},
{"learn":[0.4233495257],"iteration":228,"passed_time":41.22466949,"remaining_time":138.7957213},
{"learn":[0.4232290814],"iteration":229,"passed_time":41.39462484,"remaining_time":138.5820049},
{"learn":[0.4224125445],"iteration":230,"passed_time":41.62065332,"remaining_time":138.5553351},
{"learn":[0.4221596649],"iteration":231,"passed_time":41.79740936,"remaining_time":138.3638379},
{"learn":[0.4215138356],"iteration":232,"passed_time":42.00305934,"remaining_time":138.2675816},
{"learn":[0.4210984156],"iteration":233,"passed_time":42.1926816,"remaining_time":138.1179235},
{"learn":[0.4207171591],"iteration":234,"passed_time":42.38219182,"remaining_time":137.9675606},
{"learn":[0.4198014252],"iteration":235,"passed_time":42.58562248,"remaining_time":137.8619304},
{"learn":[0.4190737324],"iteration":236,"passed_time":42.76065402,"remaining_time":137.6640465},
{"learn":[0.4184911726],"iteration":237,"passed_time":42.96154883,"remaining_time":137.5491605},
{"learn":[0.4181332972],"iteration":238,"passed_time":43.1473511,"remaining_time":137.3854987},
{"learn":[0.4177150481],"iteration":239,"passed_time":43.3142866,"remaining_time":137.1619076},
{"learn":[0.4171355948],"iteration":240,"passed_time":43.50922673,"remaining_time":137.0269838},
{"learn":[0.4165734877],"iteration":241,"passed_time":43.70859481,"remaining_time":136.9054333},
{"learn":[0.4160525674],"iteration":242,"passed_time":43.9068056,"remaining_time":136.7796372},
{"learn":[0.4156684022],"iteration":243,"passed_time":44.11258097,"remaining_time":136.6766853},
{"learn":[0.4151122441],"iteration":244,"passed_time":44.31608661,"remaining_time":136.5658995},
{"learn":[0.4145427452],"iteration":245,"passed_time":44.50916654,"remaining_time":136.4224048},
{"learn":[0.4142513695],"iteration":246,"passed_time":44.65797151,"remaining_time":136.1435326},
{"learn":[0.4138520619],"iteration":247,"passed_time":44.87262468,"remaining_time":136.0653781},
{"learn":[0.4134594914],"iteration":248,"passed_time":45.06313489,"remaining_time":135.9133104},
{"learn":[0.4128690948],"iteration":249,"passed_time":45.25562424,"remaining_time":135.7668727},
{"learn":[0.4127258066],"iteration":250,"passed_time":45.44438202,"remaining_time":135.6089328},
{"learn":[0.4122604892],"iteration":251,"passed_time":45.6540088,"remaining_time":135.5126928},
{"learn":[0.4115930918],"iteration":252,"passed_time":45.88961844,"remaining_time":135.4922726},
{"learn":[0.4111344788],"iteration":253,"passed_time":46.04685619,"remaining_time":135.2399792},
{"learn":[0.4106927639],"iteration":254,"passed_time":46.23511396,"remaining_time":135.0790584},
{"learn":[0.4104528976],"iteration":255,"passed_time":46.43478254,"remaining_time":134.9510868},
{"learn":[0.4099425377],"iteration":256,"passed_time":46.61775645,"remaining_time":134.774292},
{"learn":[0.4093961286],"iteration":257,"passed_time":46.86688847,"remaining_time":134.787718},
{"learn":[0.4089593268],"iteration":258,"passed_time":47.04943641,"remaining_time":134.6086192},
{"learn":[0.4084212891],"iteration":259,"passed_time":47.2329357,"remaining_time":134.4322016},
{"learn":[0.4080713181],"iteration":260,"passed_time":47.38960221,"remaining_time":134.1797549},
{"learn":[0.4075449377],"iteration":261,"passed_time":47.54903239,"remaining_time":133.9358241},
{"learn":[0.4068367834],"iteration":262,"passed_time":47.7315396,"remaining_time":133.7572041},
{"learn":[0.4064192016],"iteration":263,"passed_time":47.92873648,"remaining_time":133.6195078},
{"learn":[0.4061056756],"iteration":264,"passed_time":48.1337195,"remaining_time":133.5029578},
{"learn":[0.4053698522],"iteration":265,"passed_time":48.32126187,"remaining_time":133.3376173},
{"learn":[0.4047089852],"iteration":266,"passed_time":48.51752403,"remaining_time":133.1960491},
{"learn":[0.4042598599],"iteration":267,"passed_time":48.69451054,"remaining_time":133.0014243},
{"learn":[0.4039061508],"iteration":268,"passed_time":48.8885131,"remaining_time":132.8531713},
{"learn":[0.4032768031],"iteration":269,"passed_time":49.05947895,"remaining_time":132.6422949},
{"learn":[0.4027230471],"iteration":270,"passed_time":49.24074598,"remaining_time":132.4594237},
{"learn":[0.4024460459],"iteration":271,"passed_time":49.45061078,"remaining_time":132.3531053},
{"learn":[0.4021959925],"iteration":272,"passed_time":49.64577337,"remaining_time":132.2068763},
{"learn":[0.4016131478],"iteration":273,"passed_time":49.85216246,"remaining_time":132.0900363},
{"learn":[0.4012345985],"iteration":274,"passed_time":50.0376131,"remaining_time":131.9173436},
{"learn":[0.4007215989],"iteration":275,"passed_time":50.25229119,"remaining_time":131.8212276},
{"learn":[0.4003756145],"iteration":276,"passed_time":50.40241138,"remaining_time":131.5557524},
{"learn":[0.3998685266],"iteration":277,"passed_time":50.62137862,"remaining_time":131.4699114},
{"learn":[0.3990264609],"iteration":278,"passed_time":50.81760721,"remaining_time":131.3243541},
{"learn":[0.398583284],"iteration":279,"passed_time":51.01827705,"remaining_time":131.1898553},
{"learn":[0.3976195818],"iteration":280,"passed_time":51.24907363,"remaining_time":131.1319713},
{"learn":[0.3969047825],"iteration":281,"passed_time":51.45861067,"remaining_time":131.0187321},
{"learn":[0.396500791],"iteration":282,"passed_time":51.66454972,"remaining_time":130.8956966},
{"learn":[0.3958469847],"iteration":283,"passed_time":51.83672585,"remaining_time":130.6869567},
{"learn":[0.3951678758],"iteration":284,"passed_time":52.04884147,"remaining_time":130.5786725},
{"learn":[0.3945699547],"iteration":285,"passed_time":52.2323538,"remaining_time":130.3982539},
{"learn":[0.3939303762],"iteration":286,"passed_time":52.43024225,"remaining_time":130.2535286},
{"learn":[0.3932253086],"iteration":287,"passed_time":52.62275029,"remaining_time":130.0951327},
{"learn":[0.3926409067],"iteration":288,"passed_time":52.83001152,"remaining_time":129.9727965},
{"learn":[0.391899098],"iteration":289,"passed_time":53.06038927,"remaining_time":129.9064703},
{"learn":[0.3912778541],"iteration":290,"passed_time":53.20855098,"remaining_time":129.6387032},
{"learn":[0.3909094354],"iteration":291,"passed_time":53.3998318,"remaining_time":129.4763045},
{"learn":[0.3903660624],"iteration":292,"passed_time":53.57455178,"remaining_time":129.2737478},
{"learn":[0.3899486209],"iteration":293,"passed_time":53.76253962,"remaining_time":129.1032414},
{"learn":[0.3895394763],"iteration":294,"passed_time":53.95461856,"remaining_time":128.9423935},
{"learn":[0.3891669681],"iteration":295,"passed_time":54.15417116,"remaining_time":128.7991098},
{"learn":[0.3888192728],"iteration":296,"passed_time":54.35173302,"remaining_time":128.6507351},
{"learn":[0.3881678879],"iteration":297,"passed_time":54.54266091,"remaining_time":128.4864025},
{"learn":[0.3877735281],"iteration":298,"passed_time":54.71686157,"remaining_time":128.2826754},
{"learn":[0.3872086956],"iteration":299,"passed_time":54.90290645,"remaining_time":128.1067817},
{"learn":[0.3867391353],"iteration":300,"passed_time":55.0969048,"remaining_time":127.9492905},
{"learn":[0.386259906],"iteration":301,"passed_time":55.29344968,"remaining_time":127.7974433},
{"learn":[0.3858435262],"iteration":302,"passed_time":55.51198467,"remaining_time":127.6958855},
{"learn":[0.3851409517],"iteration":303,"passed_time":55.72002952,"remaining_time":127.5695413},
{"learn":[0.3847237537],"iteration":304,"passed_time":55.94177543,"remaining_time":127.4738817},
{"learn":[0.3840816847],"iteration":305,"passed_time":56.11058171,"remaining_time":127.2573324},
{"learn":[0.3835767468],"iteration":306,"passed_time":56.33343521,"remaining_time":127.1630964},
{"learn":[0.3831478922],"iteration":307,"passed_time":56.5238583,"remaining_time":126.9951622},
{"learn":[0.3823083327],"iteration":308,"passed_time":56.74258649,"remaining_time":126.8903795},
{"learn":[0.3817178172],"iteration":309,"passed_time":56.89224643,"remaining_time":126.6311291},
{"learn":[0.3814298561],"iteration":310,"passed_time":57.08959179,"remaining_time":126.4782275},
{"learn":[0.3810939085],"iteration":311,"passed_time":57.30634493,"remaining_time":126.3678375},
{"learn":[0.3804504016],"iteration":312,"passed_time":57.48035217,"remaining_time":126.1629455},
{"learn":[0.3799267753],"iteration":313,"passed_time":57.64269573,"remaining_time":125.9327684},
{"learn":[0.3794550326],"iteration":314,"passed_time":57.82609012,"remaining_time":125.7487991},
{"learn":[0.37911699],"iteration":315,"passed_time":57.98638171,"remaining_time":125.5148262},
{"learn":[0.3785505679],"iteration":316,"passed_time":58.16145008,"remaining_time":125.3131559},
{"learn":[0.3781391723],"iteration":317,"passed_time":58.36378273,"remaining_time":125.1701252},
{"learn":[0.3779711201],"iteration":318,"passed_time":58.5862291,"remaining_time":125.0696615},
{"learn":[0.3774048742],"iteration":319,"passed_time":58.80804994,"remaining_time":124.9671061},
{"learn":[0.3770071056],"iteration":320,"passed_time":58.95508787,"remaining_time":124.705622},
{"learn":[0.3764441405],"iteration":321,"passed_time":59.08995812,"remaining_time":124.4192286},
{"learn":[0.3760800966],"iteration":322,"passed_time":59.3095856,"remaining_time":124.3114225},
{"learn":[0.3757549305],"iteration":323,"passed_time":59.51922268,"remaining_time":124.1820819},
{"learn":[0.3754409763],"iteration":324,"passed_time":59.69199193,"remaining_time":123.9756755},
{"learn":[0.3750522005],"iteration":325,"passed_time":59.90088553,"remaining_time":123.8441621},
{"learn":[0.3745506705],"iteration":326,"passed_time":60.1410518,"remaining_time":123.7765378},
{"learn":[0.3743946917],"iteration":327,"passed_time":60.33781306,"remaining_time":123.6189341},
{"learn":[0.3741098499],"iteration":328,"passed_time":60.53527125,"remaining_time":123.4625137},
{"learn":[0.3737762814],"iteration":329,"passed_time":60.75564035,"remaining_time":123.3523607},
{"learn":[0.3732861929],"iteration":330,"passed_time":60.95129478,"remaining_time":123.1915897},
{"learn":[0.3728757225],"iteration":331,"passed_time":61.16846002,"remaining_time":123.0738894},
{"learn":[0.3725669508],"iteration":332,"passed_time":61.36901902,"remaining_time":122.9223294},
{"learn":[0.3723261437],"iteration":333,"passed_time":61.55259161,"remaining_time":122.7366048},
{"learn":[0.3722161226],"iteration":334,"passed_time":61.7173483,"remaining_time":122.5135421},
{"learn":[0.3716653732],"iteration":335,"passed_time":61.88749072,"remaining_time":122.3014698},
{"learn":[0.3713825315],"iteration":336,"passed_time":62.07339352,"remaining_time":122.1206525},
{"learn":[0.3708016866],"iteration":337,"passed_time":62.31336091,"remaining_time":122.045695},
{"learn":[0.3704612692],"iteration":338,"passed_time":62.52089679,"remaining_time":121.9065274},
{"learn":[0.3700068228],"iteration":339,"passed_time":62.70695865,"remaining_time":121.7252727},
{"learn":[0.3697805824],"iteration":340,"passed_time":62.89292116,"remaining_time":121.5437978},
{"learn":[0.3691889793],"iteration":341,"passed_time":63.08802021,"remaining_time":121.3798751},
{"learn":[0.368939562],"iteration":342,"passed_time":63.23778186,"remaining_time":121.1289291},
{"learn":[0.3687127126],"iteration":343,"passed_time":63.41975253,"remaining_time":120.9399932},
{"learn":[0.3685892544],"iteration":344,"passed_time":63.61135652,"remaining_time":120.769387},
{"learn":[0.3681084587],"iteration":345,"passed_time":63.79913742,"remaining_time":120.5914332},
{"learn":[0.3675630763],"iteration":346,"passed_time":64.00071284,"remaining_time":120.4393818},
{"learn":[0.3674156394],"iteration":347,"passed_time":64.21329734,"remaining_time":120.307672},
{"learn":[0.3670198862],"iteration":348,"passed_time":64.41470529,"remaining_time":120.1546508},
{"learn":[0.366630764],"iteration":349,"passed_time":64.57180297,"remaining_time":119.9190627},
{"learn":[0.3661694686],"iteration":350,"passed_time":64.75806853,"remaining_time":119.7378532},
{"learn":[0.3657289622],"iteration":351,"passed_time":64.95180298,"remaining_time":119.5703646},
{"learn":[0.365295327],"iteration":352,"passed_time":65.15187512,"remaining_time":119.4143434},
{"learn":[0.3648700535],"iteration":353,"passed_time":65.36343153,"remaining_time":119.2790304},
{"learn":[0.3645041214],"iteration":354,"passed_time":65.55007303,"remaining_time":119.09802},
{"learn":[0.3642336159],"iteration":355,"passed_time":65.75843431,"remaining_time":118.9562688},
{"learn":[0.363980622],"iteration":356,"passed_time":65.99126491,"remaining_time":118.8582166},
{"learn":[0.3636436418],"iteration":357,"passed_time":66.14617485,"remaining_time":118.6196767},
{"learn":[0.3631751342],"iteration":358,"passed_time":66.35192304,"remaining_time":118.4723751},
{"learn":[0.3628716311],"iteration":359,"passed_time":66.55175262,"remaining_time":118.3142269},
{"learn":[0.3623161005],"iteration":360,"passed_time":66.74053734,"remaining_time":118.1362974},
{"learn":[0.3621626678],"iteration":361,"passed_time":66.90991469,"remaining_time":117.9241038},
{"learn":[0.3616989284],"iteration":362,"passed_time":67.07963377,"remaining_time":117.7127458},
{"learn":[0.3614014198],"iteration":363,"passed_time":67.27819779,"remaining_time":117.5520159},
{"learn":[0.3608661473],"iteration":364,"passed_time":67.45189548,"remaining_time":117.3478182},
{"learn":[0.3607563141],"iteration":365,"passed_time":67.61876322,"remaining_time":117.131956},
{"learn":[0.3606083633],"iteration":366,"passed_time":67.8352422,"remaining_time":117.00193},
{"learn":[0.3600000877],"iteration":367,"passed_time":68.01799923,"remaining_time":116.8135204},
{"learn":[0.3596614383],"iteration":368,"passed_time":68.13456066,"remaining_time":116.5119452},
{"learn":[0.3592368775],"iteration":369,"passed_time":68.25933787,"remaining_time":116.2253591},
{"learn":[0.3589148152],"iteration":370,"passed_time":68.45889151,"remaining_time":116.0664225},
{"learn":[0.358229052],"iteration":371,"passed_time":68.66283838,"remaining_time":115.9146841},
{"learn":[0.357632672],"iteration":372,"passed_time":68.83927729,"remaining_time":115.7164259},
{"learn":[0.357305287],"iteration":373,"passed_time":69.01060138,"remaining_time":115.5097232},
{"learn":[0.3571150677],"iteration":374,"passed_time":69.20437001,"remaining_time":115.3406167},
{"learn":[0.3568389341],"iteration":375,"passed_time":69.42478345,"remaining_time":115.2155981},
{"learn":[0.3566751339],"iteration":376,"passed_time":69.60494029,"remaining_time":115.0235485},
{"learn":[0.3563170811],"iteration":377,"passed_time":69.80736712,"remaining_time":114.8682073},
{"learn":[0.3559111704],"iteration":378,"passed_time":70.01453134,"remaining_time":114.7203798},
{"learn":[0.3555309306],"iteration":379,"passed_time":70.22300371,"remaining_time":114.5743745},
{"learn":[0.3550737561],"iteration":380,"passed_time":70.39128089,"remaining_time":114.3627372},
{"learn":[0.3544199319],"iteration":381,"passed_time":70.59181831,"remaining_time":114.2035176},
{"learn":[0.3541429372],"iteration":382,"passed_time":70.79100095,"remaining_time":114.0418997},
{"learn":[0.3536977741],"iteration":383,"passed_time":70.97990437,"remaining_time":113.8635966},
{"learn":[0.3533506814],"iteration":384,"passed_time":71.16013402,"remaining_time":113.6713829},
{"learn":[0.3528456418],"iteration":385,"passed_time":71.34290894,"remaining_time":113.48328},
{"learn":[0.3523526451],"iteration":386,"passed_time":71.52924002,"remaining_time":113.3008375},
{"learn":[0.3518233292],"iteration":387,"passed_time":71.66587869,"remaining_time":113.0399942},
{"learn":[0.3513921058],"iteration":388,"passed_time":71.82800063,"remaining_time":112.8198159},
{"learn":[0.3511352269],"iteration":389,"passed_time":72.00885301,"remaining_time":112.6292316},
{"learn":[0.3508002363],"iteration":390,"passed_time":72.2059494,"remaining_time":112.4639979},
{"learn":[0.3504362332],"iteration":391,"passed_time":72.42760974,"remaining_time":112.3367008},
{"learn":[0.3501932576],"iteration":392,"passed_time":72.62872995,"remaining_time":112.1771987},
{"learn":[0.3499878689],"iteration":393,"passed_time":72.82354352,"remaining_time":112.0077852},
{"learn":[0.3497084078],"iteration":394,"passed_time":73.01544192,"remaining_time":111.8337781},
{"learn":[0.3493684496],"iteration":395,"passed_time":73.19698858,"remaining_time":111.6438917},
{"learn":[0.349079036],"iteration":396,"passed_time":73.38245746,"remaining_time":111.4600047},
{"learn":[0.3487302775],"iteration":397,"passed_time":73.58636237,"remaining_time":111.3039953},
{"learn":[0.3483874973],"iteration":398,"passed_time":73.7628129,"remaining_time":111.1063924},
{"learn":[0.3478481611],"iteration":399,"passed_time":73.97391466,"remaining_time":110.960872},
{"learn":[0.3475392389],"iteration":400,"passed_time":74.17906558,"remaining_time":110.8061354},
{"learn":[0.347096708],"iteration":401,"passed_time":74.37345439,"remaining_time":110.6351386},
{"learn":[0.3466783692],"iteration":402,"passed_time":74.57692965,"remaining_time":110.4774864},
{"learn":[0.3462297192],"iteration":403,"passed_time":74.74769092,"remaining_time":110.271346},
{"learn":[0.346049906],"iteration":404,"passed_time":74.92203927,"remaining_time":110.0706503},
{"learn":[0.3455140217],"iteration":405,"passed_time":75.14447491,"remaining_time":109.9404387},
{"learn":[0.3450994492],"iteration":406,"passed_time":75.34344704,"remaining_time":109.7755875},
{"learn":[0.344537751],"iteration":407,"passed_time":75.54708335,"remaining_time":109.6173366},
{"learn":[0.3441901279],"iteration":408,"passed_time":75.73147379,"remaining_time":109.4310538},
{"learn":[0.3439020025],"iteration":409,"passed_time":75.9452752,"remaining_time":109.2871033},
{"learn":[0.3435307494],"iteration":410,"passed_time":76.10011541,"remaining_time":109.0583162},
{"learn":[0.3432977349],"iteration":411,"passed_time":76.2451312,"remaining_time":108.8158669},
{"learn":[0.3428890777],"iteration":412,"passed_time":76.46590642,"remaining_time":108.6815668},
{"learn":[0.3424289257],"iteration":413,"passed_time":76.68025535,"remaining_time":108.5377527},
{"learn":[0.3422010787],"iteration":414,"passed_time":76.87959134,"remaining_time":108.372436},
{"learn":[0.3419354562],"iteration":415,"passed_time":77.08686901,"remaining_time":108.2181046},
{"learn":[0.3417761115],"iteration":416,"passed_time":77.2870557,"remaining_time":108.0536055},
{"learn":[0.3413937719],"iteration":417,"passed_time":77.50775475,"remaining_time":107.9174958},
{"learn":[0.3411181966],"iteration":418,"passed_time":77.66419408,"remaining_time":107.6918777},
{"learn":[0.3407403796],"iteration":419,"passed_time":77.85386686,"remaining_time":107.5124828},
{"learn":[0.3404273225],"iteration":420,"passed_time":78.0489277,"remaining_time":107.3404493},
{"learn":[0.3401339574],"iteration":421,"passed_time":78.23780756,"remaining_time":107.1598407},
{"learn":[0.339736948],"iteration":422,"passed_time":78.44290098,"remaining_time":107.0013094},
{"learn":[0.3394147406],"iteration":423,"passed_time":78.64430882,"remaining_time":106.8375516},
{"learn":[0.3389679701],"iteration":424,"passed_time":78.834438,"remaining_time":106.6583573},
{"learn":[0.3387162531],"iteration":425,"passed_time":78.99928332,"remaining_time":106.4450437},
{"learn":[0.3385438315],"iteration":426,"passed_time":79.18527947,"remaining_time":106.2603399},
{"learn":[0.3382667971],"iteration":427,"passed_time":79.39284905,"remaining_time":106.1044618},
{"learn":[0.3378039433],"iteration":428,"passed_time":79.57188193,"remaining_time":105.9103603},
{"learn":[0.3373757256],"iteration":429,"passed_time":79.7660598,"remaining_time":105.7364049},
{"learn":[0.3369005158],"iteration":430,"passed_time":79.96698675,"remaining_time":105.5712656},
{"learn":[0.3365151788],"iteration":431,"passed_time":80.19815738,"remaining_time":105.4457254},
{"learn":[0.3360022109],"iteration":432,"passed_time":80.39370684,"remaining_time":105.2730526},
{"learn":[0.3357762666],"iteration":433,"passed_time":80.59010404,"remaining_time":105.1013799},
{"learn":[0.3354778671],"iteration":434,"passed_time":80.7800153,"remaining_time":104.9211693},
{"learn":[0.3352371032],"iteration":435,"passed_time":80.9856868,"remaining_time":104.7613013},
{"learn":[0.3348663813],"iteration":436,"passed_time":81.16923699,"remaining_time":104.5727241},
{"learn":[0.3344168022],"iteration":437,"passed_time":81.36006473,"remaining_time":104.3935077},
{"learn":[0.333988727],"iteration":438,"passed_time":81.58176338,"remaining_time":104.2536885},
{"learn":[0.3337712982],"iteration":439,"passed_time":81.75122665,"remaining_time":104.0470157},
{"learn":[0.3334039637],"iteration":440,"passed_time":81.88868882,"remaining_time":103.799948},
{"learn":[0.3330875254],"iteration":441,"passed_time":82.0655429,"remaining_time":103.6031062},
{"learn":[0.3329020613],"iteration":442,"passed_time":82.27082058,"remaining_time":103.4420927},
{"learn":[0.3325693091],"iteration":443,"passed_time":82.46881239,"remaining_time":103.2717561},
{"learn":[0.3321890441],"iteration":444,"passed_time":82.67279707,"remaining_time":103.1087694},
{"learn":[0.3318096326],"iteration":445,"passed_time":82.90541756,"remaining_time":102.9811689},
{"learn":[0.3315733283],"iteration":446,"passed_time":83.08888438,"remaining_time":102.7922887},
{"learn":[0.3314197075],"iteration":447,"passed_time":83.24264788,"remaining_time":102.566834},
{"learn":[0.3310419368],"iteration":448,"passed_time":83.39874,"remaining_time":102.3445562},
{"learn":[0.3307848087],"iteration":449,"passed_time":83.6021475,"remaining_time":102.1804025},
{"learn":[0.3304218723],"iteration":450,"passed_time":83.80384635,"remaining_time":102.0139948},
{"learn":[0.3301185636],"iteration":451,"passed_time":83.99705835,"remaining_time":101.8371415},
{"learn":[0.3299632351],"iteration":452,"passed_time":84.22296088,"remaining_time":101.6996901},
{"learn":[0.329788119],"iteration":453,"passed_time":84.44121844,"remaining_time":101.5526548},
{"learn":[0.3294612223],"iteration":454,"passed_time":84.64678369,"remaining_time":101.3901035},
{"learn":[0.3291662979],"iteration":455,"passed_time":84.81414538,"remaining_time":101.1817875},
{"learn":[0.3288776052],"iteration":456,"passed_time":84.99461337,"remaining_time":100.9892233},
{"learn":[0.3284632996],"iteration":457,"passed_time":85.20075413,"remaining_time":100.8270933},
{"learn":[0.328242403],"iteration":458,"passed_time":85.39157794,"remaining_time":100.6467182},
{"learn":[0.3279299216],"iteration":459,"passed_time":85.57929657,"remaining_time":100.4626525},
{"learn":[0.3276227072],"iteration":460,"passed_time":85.7772393,"remaining_time":100.2905249},
{"learn":[0.3271398226],"iteration":461,"passed_time":85.98960657,"remaining_time":100.135083},
{"learn":[0.3268364027],"iteration":462,"passed_time":86.15883109,"remaining_time":99.92935701},
{"learn":[0.3265331051],"iteration":463,"passed_time":86.30845861,"remaining_time":99.70115047},
{"learn":[0.3261943954],"iteration":464,"passed_time":86.48432182,"remaining_time":99.50346704},
{"learn":[0.3259114378],"iteration":465,"passed_time":86.68658787,"remaining_time":99.33613288},
{"learn":[0.3257855941],"iteration":466,"passed_time":86.89295068,"remaining_time":99.17332487},
{"learn":[0.325533287],"iteration":467,"passed_time":87.09831423,"remaining_time":99.00919481},
{"learn":[0.3250847776],"iteration":468,"passed_time":87.31422976,"remaining_time":98.85683583},
{"learn":[0.3247654757],"iteration":469,"passed_time":87.5301251,"remaining_time":98.70418362},
{"learn":[0.3243287197],"iteration":470,"passed_time":87.69279939,"remaining_time":98.49148806},
{"learn":[0.3239233623],"iteration":471,"passed_time":87.85968556,"remaining_time":98.28371605},
{"learn":[0.3237264117],"iteration":472,"passed_time":88.06420718,"remaining_time":98.11804901},
{"learn":[0.3235472833],"iteration":473,"passed_time":88.29400148,"remaining_time":97.98026324},
{"learn":[0.3231652689],"iteration":474,"passed_time":88.49508419,"remaining_time":97.81035621},
{"learn":[0.3227435259],"iteration":475,"passed_time":88.69089781,"remaining_time":97.63451776},
{"learn":[0.3221699555],"iteration":476,"passed_time":88.88604163,"remaining_time":97.45786115},
{"learn":[0.3220429955],"iteration":477,"passed_time":89.04473525,"remaining_time":97.24132175},
{"learn":[0.3218297841],"iteration":478,"passed_time":89.20564496,"remaining_time":97.02743429},
{"learn":[0.3216696795],"iteration":479,"passed_time":89.39818788,"remaining_time":96.84803687},
{"learn":[0.3212905844],"iteration":480,"passed_time":89.59280828,"remaining_time":96.6708264},
{"learn":[0.3209411378],"iteration":481,"passed_time":89.7923524,"remaining_time":96.49883515},
{"learn":[0.3205391631],"iteration":482,"passed_time":89.98093631,"remaining_time":96.31499808},
{"learn":[0.3201868591],"iteration":483,"passed_time":90.17425129,"remaining_time":96.13618526},
{"learn":[0.31990685],"iteration":484,"passed_time":90.3678618,"remaining_time":95.95762645},
{"learn":[0.3195151553],"iteration":485,"passed_time":90.54241119,"remaining_time":95.75884641},
{"learn":[0.3192320579],"iteration":486,"passed_time":90.73794549,"remaining_time":95.58227112},
{"learn":[0.3187011259],"iteration":487,"passed_time":90.94728853,"remaining_time":95.420106},
{"learn":[0.3184325508],"iteration":488,"passed_time":91.13550842,"remaining_time":95.23567444},
{"learn":[0.3182112711],"iteration":489,"passed_time":91.33308755,"remaining_time":95.06096867},
{"learn":[0.3177480712],"iteration":490,"passed_time":91.52881805,"remaining_time":94.88425334},
{"learn":[0.3174116814],"iteration":491,"passed_time":91.76147206,"remaining_time":94.74558497},
{"learn":[0.3171273333],"iteration":492,"passed_time":91.93342624,"remaining_time":94.54411178},
{"learn":[0.3167391344],"iteration":493,"passed_time":92.07630527,"remaining_time":94.31297666},
{"learn":[0.316508405],"iteration":494,"passed_time":92.26779086,"remaining_time":94.13178663},
{"learn":[0.3163131872],"iteration":495,"passed_time":92.45899616,"remaining_time":93.95027029},
{"learn":[0.3160925348],"iteration":496,"passed_time":92.64293905,"remaining_time":93.76136488},
{"learn":[0.3157307051],"iteration":497,"passed_time":92.84632794,"remaining_time":93.59208157},
{"learn":[0.3152729646],"iteration":498,"passed_time":93.03748581,"remaining_time":93.41038154},
{"learn":[0.3149891971],"iteration":499,"passed_time":93.20472813,"remaining_time":93.20472813},
{"learn":[0.314745357],"iteration":500,"passed_time":93.37710155,"remaining_time":93.00433866},
{"learn":[0.3144063314],"iteration":501,"passed_time":93.56951901,"remaining_time":92.82394515},
{"learn":[0.3141255634],"iteration":502,"passed_time":93.74487102,"remaining_time":92.62664194},
{"learn":[0.3137976447],"iteration":503,"passed_time":93.99670948,"remaining_time":92.50469822},
{"learn":[0.313438543],"iteration":504,"passed_time":94.20278773,"remaining_time":92.337386},
{"learn":[0.3131054605],"iteration":505,"passed_time":94.39509348,"remaining_time":92.15647466},
{"learn":[0.3127912573],"iteration":506,"passed_time":94.6040993,"remaining_time":91.9917573},
{"learn":[0.3124462818],"iteration":507,"passed_time":94.78734141,"remaining_time":91.80191333},
{"learn":[0.3120183168],"iteration":508,"passed_time":94.9472348,"remaining_time":91.58957227},
{"learn":[0.3117662992],"iteration":509,"passed_time":95.13864476,"remaining_time":91.40771751},
{"learn":[0.3116276737],"iteration":510,"passed_time":95.34708174,"remaining_time":91.24211932},
{"learn":[0.3113512223],"iteration":511,"passed_time":95.56891265,"remaining_time":91.08911987},
{"learn":[0.3110276287],"iteration":512,"passed_time":95.76961627,"remaining_time":90.91579556},
{"learn":[0.3107167205],"iteration":513,"passed_time":95.96750614,"remaining_time":90.73970425},
{"learn":[0.3105394337],"iteration":514,"passed_time":96.15119367,"remaining_time":90.55015326},
{"learn":[0.310356918],"iteration":515,"passed_time":96.34684839,"remaining_time":90.37185004},
{"learn":[0.3100218464],"iteration":516,"passed_time":96.54789849,"remaining_time":90.19852025},
{"learn":[0.3097200774],"iteration":517,"passed_time":96.7253066,"remaining_time":90.00308452},
{"learn":[0.3090925059],"iteration":518,"passed_time":96.93764717,"remaining_time":89.84009304},
{"learn":[0.3089323842],"iteration":519,"passed_time":97.13997672,"remaining_time":89.66767082},
{"learn":[0.3085879383],"iteration":520,"passed_time":97.34556598,"remaining_time":89.49813072},
{"learn":[0.3084501987],"iteration":521,"passed_time":97.56555315,"remaining_time":89.34163679},
{"learn":[0.3082301524],"iteration":522,"passed_time":97.71175179,"remaining_time":89.11760154},
{"learn":[0.3078562969],"iteration":523,"passed_time":97.92880102,"remaining_time":88.95822383},
{"learn":[0.3075235251],"iteration":524,"passed_time":98.12823581,"remaining_time":88.78268954},
{"learn":[0.3071714013],"iteration":525,"passed_time":98.33057014,"remaining_time":88.60967728},
{"learn":[0.3070011208],"iteration":526,"passed_time":98.51852144,"remaining_time":88.42364448},
{"learn":[0.3067650423],"iteration":527,"passed_time":98.7047825,"remaining_time":88.23609344},
{"learn":[0.3063730373],"iteration":528,"passed_time":98.8998149,"remaining_time":88.05635694},
{"learn":[0.3060249032],"iteration":529,"passed_time":99.06700364,"remaining_time":87.85187116},
{"learn":[0.3058348375],"iteration":530,"passed_time":99.24817918,"remaining_time":87.65987954},
{"learn":[0.3055999439],"iteration":531,"passed_time":99.43188628,"remaining_time":87.4701556},
{"learn":[0.3050320327],"iteration":532,"passed_time":99.61878804,"remaining_time":87.28325331},
{"learn":[0.3044354594],"iteration":533,"passed_time":99.8075112,"remaining_time":87.09794048},
{"learn":[0.3040822816],"iteration":534,"passed_time":99.99501164,"remaining_time":86.91155217},
{"learn":[0.3038571357],"iteration":535,"passed_time":100.1841832,"remaining_time":86.72660633},
{"learn":[0.303588391],"iteration":536,"passed_time":100.3712458,"remaining_time":86.53982648},
{"learn":[0.3032927307],"iteration":537,"passed_time":100.5778735,"remaining_time":86.36984677},
{"learn":[0.302849657],"iteration":538,"passed_time":100.7972767,"remaining_time":86.21065779},
{"learn":[0.3026990815],"iteration":539,"passed_time":100.9928428,"remaining_time":86.03094016},
{"learn":[0.3022520623],"iteration":540,"passed_time":101.2227084,"remaining_time":85.88026464},
{"learn":[0.3019693854],"iteration":541,"passed_time":101.4262224,"remaining_time":85.70702929},
{"learn":[0.3016916948],"iteration":542,"passed_time":101.6217329,"remaining_time":85.52694646},
{"learn":[0.3012416293],"iteration":543,"passed_time":101.8390548,"remaining_time":85.36509008},
{"learn":[0.300945098],"iteration":544,"passed_time":102.0173555,"remaining_time":85.17045272},
{"learn":[0.3006965991],"iteration":545,"passed_time":102.1545108,"remaining_time":84.94166282},
{"learn":[0.3006083458],"iteration":546,"passed_time":102.2932226,"remaining_time":84.71449698},
{"learn":[0.3003962619],"iteration":547,"passed_time":102.4602354,"remaining_time":84.51099709},
{"learn":[0.3002609383],"iteration":548,"passed_time":102.6000498,"remaining_time":84.28528683},
{"learn":[0.3001997516],"iteration":549,"passed_time":102.7647751,"remaining_time":84.08027053},
{"learn":[0.2999207679],"iteration":550,"passed_time":102.9259907,"remaining_time":83.87254054},
{"learn":[0.2995659888],"iteration":551,"passed_time":103.0959607,"remaining_time":83.67208404},
{"learn":[0.2991764847],"iteration":552,"passed_time":103.2560685,"remaining_time":83.46376606},
{"learn":[0.2989226407],"iteration":553,"passed_time":103.3861556,"remaining_time":83.23145377},
{"learn":[0.2987005111],"iteration":554,"passed_time":103.5146048,"remaining_time":82.99819667},
{"learn":[0.2985513193],"iteration":555,"passed_time":103.6690047,"remaining_time":82.78603974},
{"learn":[0.2980711635],"iteration":556,"passed_time":103.8292591,"remaining_time":82.5787465},
{"learn":[0.2978149941],"iteration":557,"passed_time":103.9716475,"remaining_time":82.35746989},
{"learn":[0.2972984411],"iteration":558,"passed_time":104.1480919,"remaining_time":82.16334261},
{"learn":[0.2970642006],"iteration":559,"passed_time":104.3150625,"remaining_time":81.96183483},
{"learn":[0.2967198562],"iteration":560,"passed_time":104.4826701,"remaining_time":81.76094862},
{"learn":[0.2965106332],"iteration":561,"passed_time":104.6409835,"remaining_time":81.55293735},
{"learn":[0.2962337],"iteration":562,"passed_time":104.7719294,"remaining_time":81.32385995},
{"learn":[0.2958910449],"iteration":563,"passed_time":104.9207535,"remaining_time":81.10895131},
{"learn":[0.2956978149],"iteration":564,"passed_time":105.0754986,"remaining_time":80.89883517},
{"learn":[0.2953810034],"iteration":565,"passed_time":105.2524419,"remaining_time":80.70593598},
{"learn":[0.2951156286],"iteration":566,"passed_time":105.4248922,"remaining_time":80.50966196},
{"learn":[0.2947923286],"iteration":567,"passed_time":105.5906793,"remaining_time":80.30840401},
{"learn":[0.2944921466],"iteration":568,"passed_time":105.7525487,"remaining_time":80.10430313},
{"learn":[0.2941191142],"iteration":569,"passed_time":105.9238472,"remaining_time":79.90746367},
{"learn":[0.2937033063],"iteration":570,"passed_time":106.07948,"remaining_time":79.69894385},
{"learn":[0.2933796985],"iteration":571,"passed_time":106.2178277,"remaining_time":79.47767527},
{"learn":[0.2931253868],"iteration":572,"passed_time":106.3745775,"remaining_time":79.27040942},
{"learn":[0.292828918],"iteration":573,"passed_time":106.5360372,"remaining_time":79.06681506},
{"learn":[0.2925712403],"iteration":574,"passed_time":106.7019746,"remaining_time":78.86667687},
{"learn":[0.2922780401],"iteration":575,"passed_time":106.8614126,"remaining_time":78.66187319},
{"learn":[0.2918354848],"iteration":576,"passed_time":107.0387177,"remaining_time":78.4703251},
{"learn":[0.2914970188],"iteration":577,"passed_time":107.2440812,"remaining_time":78.29931186},
{"learn":[0.2911682255],"iteration":578,"passed_time":107.4079901,"remaining_time":78.09803767},
{"learn":[0.2909619545],"iteration":579,"passed_time":107.5445288,"remaining_time":77.87707258},
{"learn":[0.2907513687],"iteration":580,"passed_time":107.737554,"remaining_time":77.69713449},
{"learn":[0.2905410758],"iteration":581,"passed_time":107.9515404,"remaining_time":77.53220601},
{"learn":[0.2901277753],"iteration":582,"passed_time":108.117519,"remaining_time":77.33277086},
{"learn":[0.290001381],"iteration":583,"passed_time":108.3126965,"remaining_time":77.15424956},
{"learn":[0.2897756187],"iteration":584,"passed_time":108.4844896,"remaining_time":76.95908237},
{"learn":[0.2896488991],"iteration":585,"passed_time":108.6709528,"remaining_time":76.77435914},
{"learn":[0.2894981757],"iteration":586,"passed_time":108.8181417,"remaining_time":76.56199749},
{"learn":[0.2889854319],"iteration":587,"passed_time":108.9613674,"remaining_time":76.34708056},
{"learn":[0.2886337373],"iteration":588,"passed_time":109.1427884,"remaining_time":76.1590595},
{"learn":[0.2885440943],"iteration":589,"passed_time":109.3268695,"remaining_time":75.97290932},
{"learn":[0.2882941406],"iteration":590,"passed_time":109.484743,"remaining_time":75.76862925},
{"learn":[0.2880242952],"iteration":591,"passed_time":109.6967778,"remaining_time":75.60183335},
{"learn":[0.2877105341],"iteration":592,"passed_time":109.8784695,"remaining_time":75.41405916},
{"learn":[0.2875844012],"iteration":593,"passed_time":110.0792038,"remaining_time":75.23932108},
{"learn":[0.2873893181],"iteration":594,"passed_time":110.2196458,"remaining_time":75.02345642},
{"learn":[0.2870645393],"iteration":595,"passed_time":110.3982091,"remaining_time":74.83368539},
{"learn":[0.2868528565],"iteration":596,"passed_time":110.6038994,"remaining_time":74.66226372},
{"learn":[0.286636452],"iteration":597,"passed_time":110.7797699,"remaining_time":74.47068143},
{"learn":[0.286236186],"iteration":598,"passed_time":110.9273884,"remaining_time":74.26023834},
{"learn":[0.2860878292],"iteration":599,"passed_time":111.107895,"remaining_time":74.07193002},
{"learn":[0.2858237976],"iteration":600,"passed_time":111.2936762,"remaining_time":73.88714945},
{"learn":[0.2856264798],"iteration":601,"passed_time":111.4604161,"remaining_time":73.68977675},
{"learn":[0.285462554],"iteration":602,"passed_time":111.6057258,"remaining_time":73.47839661},
{"learn":[0.2851092874],"iteration":603,"passed_time":111.7537973,"remaining_time":73.26904592},
{"learn":[0.2847273824],"iteration":604,"passed_time":111.9491264,"remaining_time":73.09075194},
{"learn":[0.284344843],"iteration":605,"passed_time":112.1195599,"remaining_time":72.89621549},
{"learn":[0.2841129036],"iteration":606,"passed_time":112.2738728,"remaining_time":72.69132124},
{"learn":[0.283849014],"iteration":607,"passed_time":112.3963921,"remaining_time":72.46609488},
{"learn":[0.2836437318],"iteration":608,"passed_time":112.5506183,"remaining_time":72.26156279},
{"learn":[0.2833395846],"iteration":609,"passed_time":112.7326119,"remaining_time":72.07494861},
{"learn":[0.2831769751],"iteration":610,"passed_time":112.8824765,"remaining_time":71.86789423},
{"learn":[0.2828647873],"iteration":611,"passed_time":113.0457448,"remaining_time":71.66952448},
{"learn":[0.2827076646],"iteration":612,"passed_time":113.2255807,"remaining_time":71.48172875},
{"learn":[0.2824554199],"iteration":613,"passed_time":113.3997153,"remaining_time":71.29037476},
{"learn":[0.2820688904],"iteration":614,"passed_time":113.5777145,"remaining_time":71.10149609},
{"learn":[0.2817996555],"iteration":615,"passed_time":113.760656,"remaining_time":70.91573362},
{"learn":[0.2814895627],"iteration":616,"passed_time":113.9532256,"remaining_time":70.73595692},
{"learn":[0.2811935841],"iteration":617,"passed_time":114.1416219,"remaining_time":70.5535592},
{"learn":[0.2808589951],"iteration":618,"passed_time":114.3081556,"remaining_time":70.35768544},
{"learn":[0.2806197022],"iteration":619,"passed_time":114.4800745,"remaining_time":70.16520697},
{"learn":[0.2802440946],"iteration":620,"passed_time":114.6852688,"remaining_time":69.99310287},
{"learn":[0.2800761517],"iteration":621,"passed_time":114.8648721,"remaining_time":69.8053403},
{"learn":[0.2798429291],"iteration":622,"passed_time":115.0627726,"remaining_time":69.62867622},
{"learn":[0.2794393189],"iteration":623,"passed_time":115.268045,"remaining_time":69.4563861},
{"learn":[0.2792435821],"iteration":624,"passed_time":115.4621466,"remaining_time":69.27728793},
{"learn":[0.279124363],"iteration":625,"passed_time":115.6813308,"remaining_time":69.11312736},
{"learn":[0.2788319739],"iteration":626,"passed_time":115.8301913,"remaining_time":68.90695591},
{"learn":[0.2785612371],"iteration":627,"passed_time":116.0245312,"remaining_time":68.727907},
{"learn":[0.2779981285],"iteration":628,"passed_time":116.2381267,"remaining_time":68.56016693},
{"learn":[0.277505808],"iteration":629,"passed_time":116.4453917,"remaining_time":68.38856338},
{"learn":[0.2772200862],"iteration":630,"passed_time":116.6808203,"remaining_time":68.23331644},
{"learn":[0.2770209813],"iteration":631,"passed_time":116.8781389,"remaining_time":68.05562518},
{"learn":[0.2768996034],"iteration":632,"passed_time":117.0440878,"remaining_time":67.85968442},
{"learn":[0.2766561995],"iteration":633,"passed_time":117.2249445,"remaining_time":67.67244429},
{"learn":[0.2765028326],"iteration":634,"passed_time":117.3944732,"remaining_time":67.47871294},
{"learn":[0.2760687546],"iteration":635,"passed_time":117.6022781,"remaining_time":67.30696419},
{"learn":[0.2758091844],"iteration":636,"passed_time":117.7973831,"remaining_time":67.12786511},
{"learn":[0.2756695733],"iteration":637,"passed_time":118.0007105,"remaining_time":66.95338119},
{"learn":[0.2754488261],"iteration":638,"passed_time":118.1930974,"remaining_time":66.77262622},
{"learn":[0.2752426624],"iteration":639,"passed_time":118.4029527,"remaining_time":66.60166089},
{"learn":[0.2750252961],"iteration":640,"passed_time":118.5883602,"remaining_time":66.41688194},
{"learn":[0.2745597851],"iteration":641,"passed_time":118.7495699,"remaining_time":66.21860753},
{"learn":[0.2742852053],"iteration":642,"passed_time":118.9009451,"remaining_time":66.01498816},
{"learn":[0.2739876905],"iteration":643,"passed_time":119.121915,"remaining_time":65.85000272},
{"learn":[0.2734688667],"iteration":644,"passed_time":119.2932779,"remaining_time":65.65754056},
{"learn":[0.2730400746],"iteration":645,"passed_time":119.4802532,"remaining_time":65.47369913},
{"learn":[0.2727595744],"iteration":646,"passed_time":119.6838625,"remaining_time":65.29892345},
{"learn":[0.2725715289],"iteration":647,"passed_time":119.8840647,"remaining_time":65.12220799},
{"learn":[0.2724537388],"iteration":648,"passed_time":120.0626007,"remaining_time":64.93370238},
{"learn":[0.272202059],"iteration":649,"passed_time":120.2248078,"remaining_time":64.736435},
{"learn":[0.2719466446],"iteration":650,"passed_time":120.4186093,"remaining_time":64.55621297},
{"learn":[0.2717187477],"iteration":651,"passed_time":120.5974231,"remaining_time":64.36794976},
{"learn":[0.2714451229],"iteration":652,"passed_time":120.7963112,"remaining_time":64.19038285},
{"learn":[0.2712032797],"iteration":653,"passed_time":121.0126673,"remaining_time":64.02199216},
{"learn":[0.2707741993],"iteration":654,"passed_time":121.2078437,"remaining_time":63.84229934},
{"learn":[0.2704656849],"iteration":655,"passed_time":121.371357,"remaining_time":63.64595548},
{"learn":[0.2703269509],"iteration":656,"passed_time":121.5256556,"remaining_time":63.44490085},
{"learn":[0.2701259688],"iteration":657,"passed_time":121.7039667,"remaining_time":63.25646901},
{"learn":[0.2699614047],"iteration":658,"passed_time":121.905608,"remaining_time":63.08014012},
{"learn":[0.2698620292],"iteration":659,"passed_time":122.1135628,"remaining_time":62.90698692},
{"learn":[0.2696427077],"iteration":660,"passed_time":122.3208021,"remaining_time":62.73336143},
{"learn":[0.2694590325],"iteration":661,"passed_time":122.5187374,"remaining_time":62.55488406},
{"learn":[0.2691987144],"iteration":662,"passed_time":122.7206025,"remaining_time":62.37834547},
{"learn":[0.2690100796],"iteration":663,"passed_time":122.9169673,"remaining_time":62.19894729},
{"learn":[0.2687979563],"iteration":664,"passed_time":123.0833548,"remaining_time":62.00439678},
{"learn":[0.2684607342],"iteration":665,"passed_time":123.30588,"remaining_time":61.83808394},
{"learn":[0.2684090398],"iteration":666,"passed_time":123.5412131,"remaining_time":61.67799692},
{"learn":[0.2680217286],"iteration":667,"passed_time":123.7569683,"remaining_time":61.50795429},
{"learn":[0.2678598502],"iteration":668,"passed_time":123.9773886,"remaining_time":61.34008316},
{"learn":[0.2676080481],"iteration":669,"passed_time":124.1779599,"remaining_time":61.16227874},
{"learn":[0.2674539002],"iteration":670,"passed_time":124.3914942,"remaining_time":60.99076243},
{"learn":[0.2670902054],"iteration":671,"passed_time":124.5645772,"remaining_time":60.79937697},
{"learn":[0.2668946366],"iteration":672,"passed_time":124.7598396,"remaining_time":60.61882252},
{"learn":[0.2665906993],"iteration":673,"passed_time":124.9448882,"remaining_time":60.43328421},
{"learn":[0.2664314742],"iteration":674,"passed_time":125.1618443,"remaining_time":60.26311022},
{"learn":[0.2662034772],"iteration":675,"passed_time":125.3559995,"remaining_time":60.08186961},
{"learn":[0.2659640017],"iteration":676,"passed_time":125.5737473,"remaining_time":59.91184692},
{"learn":[0.2656399301],"iteration":677,"passed_time":125.7894176,"remaining_time":59.74069686},
{"learn":[0.2652975197],"iteration":678,"passed_time":125.944476,"remaining_time":59.5407611},
{"learn":[0.2651449197],"iteration":679,"passed_time":126.1508873,"remaining_time":59.36512343},
{"learn":[0.2650445478],"iteration":680,"passed_time":126.3493796,"remaining_time":59.1856859},
{"learn":[0.2647887129],"iteration":681,"passed_time":126.5484204,"remaining_time":59.00644822},
{"learn":[0.2644686489],"iteration":682,"passed_time":126.77211,"remaining_time":58.8385928},
{"learn":[0.2641694155],"iteration":683,"passed_time":126.9644997,"remaining_time":58.65611392},
{"learn":[0.2640270526],"iteration":684,"passed_time":127.1694627,"remaining_time":58.47938797},
{"learn":[0.2638240449],"iteration":685,"passed_time":127.3937296,"remaining_time":58.31141561},
{"learn":[0.2634433731],"iteration":686,"passed_time":127.5668092,"remaining_time":58.11995819},
{"learn":[0.263239395],"iteration":687,"passed_time":127.7462367,"remaining_time":57.93143292},
{"learn":[0.2631331069],"iteration":688,"passed_time":127.9531657,"remaining_time":57.75534764},
{"learn":[0.2629481797],"iteration":689,"passed_time":128.1688821,"remaining_time":57.58312093},
{"learn":[0.2628409598],"iteration":690,"passed_time":128.3780343,"remaining_time":57.40783299},
{"learn":[0.2625560964],"iteration":691,"passed_time":128.5929209,"remaining_time":57.23499949},
{"learn":[0.2624284222],"iteration":692,"passed_time":128.7762531,"remaining_time":57.04806594},
{"learn":[0.2620433123],"iteration":693,"passed_time":128.9118218,"remaining_time":56.84008282},
{"learn":[0.2619353763],"iteration":694,"passed_time":129.1079019,"remaining_time":56.65886343},
{"learn":[0.2617573918],"iteration":695,"passed_time":129.3192391,"remaining_time":56.48426535},
{"learn":[0.2616067373],"iteration":696,"passed_time":129.5076368,"remaining_time":56.29958958},
{"learn":[0.2613539197],"iteration":697,"passed_time":129.7005048,"remaining_time":56.11683734},
{"learn":[0.2612578759],"iteration":698,"passed_time":129.9021671,"remaining_time":55.93784304},
{"learn":[0.2609339975],"iteration":699,"passed_time":130.102971,"remaining_time":55.75841615},
{"learn":[0.2606532692],"iteration":700,"passed_time":130.2763356,"remaining_time":55.56722447},
{"learn":[0.2604440671],"iteration":701,"passed_time":130.4714095,"remaining_time":55.38529919},
{"learn":[0.2601882071],"iteration":702,"passed_time":130.6655951,"remaining_time":55.20296123},
{"learn":[0.2599481603],"iteration":703,"passed_time":130.8660415,"remaining_time":55.02322198},
{"learn":[0.2597711093],"iteration":704,"passed_time":131.0606492,"remaining_time":54.84098087},
{"learn":[0.2595948883],"iteration":705,"passed_time":131.2689632,"remaining_time":54.66441243},
{"learn":[0.2594217588],"iteration":706,"passed_time":131.3976937,"remaining_time":54.45477263},
{"learn":[0.2592165776],"iteration":707,"passed_time":131.6027441,"remaining_time":54.27683795},
{"learn":[0.258997563],"iteration":708,"passed_time":131.7747215,"remaining_time":54.08525241},
{"learn":[0.2587632103],"iteration":709,"passed_time":131.9580727,"remaining_time":53.89836773},
{"learn":[0.2585693031],"iteration":710,"passed_time":132.1902325,"remaining_time":53.73133219},
{"learn":[0.2583469056],"iteration":711,"passed_time":132.3797182,"remaining_time":53.54685229},
{"learn":[0.2581308071],"iteration":712,"passed_time":132.571054,"remaining_time":53.36310308},
{"learn":[0.2577092993],"iteration":713,"passed_time":132.7781684,"remaining_time":53.18565289},
{"learn":[0.2574813969],"iteration":714,"passed_time":132.9522782,"remaining_time":52.99496405},
{"learn":[0.2574174172],"iteration":715,"passed_time":133.119403,"remaining_time":52.8015509},
{"learn":[0.2572179343],"iteration":716,"passed_time":133.2625641,"remaining_time":52.59875262},
{"learn":[0.2570511856],"iteration":717,"passed_time":133.4725887,"remaining_time":52.42238163},
{"learn":[0.2569370964],"iteration":718,"passed_time":133.6679126,"remaining_time":52.24017169},
{"learn":[0.2567347325],"iteration":719,"passed_time":133.8627254,"remaining_time":52.05772655},
{"learn":[0.2565495444],"iteration":720,"passed_time":134.0833379,"remaining_time":51.88523061},
{"learn":[0.2562550144],"iteration":721,"passed_time":134.2864606,"remaining_time":51.70586711},
{"learn":[0.25611969],"iteration":722,"passed_time":134.4764204,"remaining_time":51.52139482},
{"learn":[0.2556505075],"iteration":723,"passed_time":134.6175605,"remaining_time":51.31829654},
{"learn":[0.255477944],"iteration":724,"passed_time":134.8180689,"remaining_time":51.1378882},
{"learn":[0.2552343375],"iteration":725,"passed_time":135.0251052,"remaining_time":50.95988819},
{"learn":[0.2548040675],"iteration":726,"passed_time":135.215379,"remaining_time":50.7755137},
{"learn":[0.2546377247],"iteration":727,"passed_time":135.4363361,"remaining_time":50.60258711},
{"learn":[0.2544629458],"iteration":728,"passed_time":135.624069,"remaining_time":50.41717791},
{"learn":[0.2540999059],"iteration":729,"passed_time":135.8187502,"remaining_time":50.23433228},
{"learn":[0.253853312],"iteration":730,"passed_time":136.0137689,"remaining_time":50.05157843},
{"learn":[0.2537251762],"iteration":731,"passed_time":136.1728892,"remaining_time":49.85564797},
{"learn":[0.2535816172],"iteration":732,"passed_time":136.3776153,"remaining_time":49.67643013},
{"learn":[0.2533772889],"iteration":733,"passed_time":136.5776118,"remaining_time":49.49542879},
{"learn":[0.2531645741],"iteration":734,"passed_time":136.7884355,"remaining_time":49.31827946},
{"learn":[0.2529389869],"iteration":735,"passed_time":136.9903339,"remaining_time":49.13783714},
{"learn":[0.2527602177],"iteration":736,"passed_time":137.2039202,"remaining_time":48.96150747},
{"learn":[0.2523717639],"iteration":737,"passed_time":137.414638,"remaining_time":48.78405848},
{"learn":[0.2521954016],"iteration":738,"passed_time":137.5690649,"remaining_time":48.5866386},
{"learn":[0.2519992336],"iteration":739,"passed_time":137.7350883,"remaining_time":48.39340942},
{"learn":[0.2517831339],"iteration":740,"passed_time":137.9353777,"remaining_time":48.21223052},
{"learn":[0.2514554289],"iteration":741,"passed_time":138.1497062,"remaining_time":48.03588166},
{"learn":[0.2513014883],"iteration":742,"passed_time":138.3785078,"remaining_time":47.86443677},
{"learn":[0.2510390756],"iteration":743,"passed_time":138.5807407,"remaining_time":47.68369572},
{"learn":[0.2508405579],"iteration":744,"passed_time":138.7556034,"remaining_time":47.49352868},
{"learn":[0.2506240001],"iteration":745,"passed_time":138.9260441,"remaining_time":47.30189707},
{"learn":[0.2503034095],"iteration":746,"passed_time":139.0990153,"remaining_time":47.11117922},
{"learn":[0.2499904177],"iteration":747,"passed_time":139.2947466,"remaining_time":46.92817667},
{"learn":[0.2496789779],"iteration":748,"passed_time":139.4941436,"remaining_time":46.74636855},
{"learn":[0.2494825841],"iteration":749,"passed_time":139.6932087,"remaining_time":46.56440291},
{"learn":[0.2493546568],"iteration":750,"passed_time":139.9068985,"remaining_time":46.38724064},
{"learn":[0.2492438556],"iteration":751,"passed_time":140.0937539,"remaining_time":46.20113162},
{"learn":[0.2489455979],"iteration":752,"passed_time":140.2902249,"remaining_time":46.01817469},
{"learn":[0.248790751],"iteration":753,"passed_time":140.4366883,"remaining_time":45.81886647},
{"learn":[0.2486075446],"iteration":754,"passed_time":140.6290112,"remaining_time":45.63457979},
{"learn":[0.2484101051],"iteration":755,"passed_time":140.8442251,"remaining_time":45.45765995},
{"learn":[0.2483129733],"iteration":756,"passed_time":141.0484343,"remaining_time":45.27710639},
{"learn":[0.2481264798],"iteration":757,"passed_time":141.2200886,"remaining_time":45.08609689},
{"learn":[0.247873354],"iteration":758,"passed_time":141.4131282,"remaining_time":44.9019287},
{"learn":[0.2475479956],"iteration":759,"passed_time":141.5636706,"remaining_time":44.70431704},
{"learn":[0.247435255],"iteration":760,"passed_time":141.698944,"remaining_time":44.50203366},
{"learn":[0.2473014464],"iteration":761,"passed_time":141.8499564,"remaining_time":44.30484203},
{"learn":[0.2468909043],"iteration":762,"passed_time":142.0327283,"remaining_time":44.11763644},
{"learn":[0.2467576079],"iteration":763,"passed_time":142.2454225,"remaining_time":43.93968547},
{"learn":[0.246579369],"iteration":764,"passed_time":142.4392002,"remaining_time":43.75583273},
{"learn":[0.2464474099],"iteration":765,"passed_time":142.677038,"remaining_time":43.58541371},
{"learn":[0.2461322844],"iteration":766,"passed_time":142.8985368,"remaining_time":43.40985539},
{"learn":[0.2459293941],"iteration":767,"passed_time":143.1000158,"remaining_time":43.22812977},
{"learn":[0.2457308761],"iteration":768,"passed_time":143.2604888,"remaining_time":43.034035},
{"learn":[0.2454993889],"iteration":769,"passed_time":143.4458558,"remaining_time":42.84746343},
{"learn":[0.2452460631],"iteration":770,"passed_time":143.6459414,"remaining_time":42.66526663},
{"learn":[0.2449879894],"iteration":771,"passed_time":143.8684174,"remaining_time":42.48963624},
{"learn":[0.2448908082],"iteration":772,"passed_time":144.0569711,"remaining_time":42.30392294},
{"learn":[0.2446604355],"iteration":773,"passed_time":144.2350061,"remaining_time":42.11513099},
{"learn":[0.2444798931],"iteration":774,"passed_time":144.4435684,"remaining_time":41.93522952},
{"learn":[0.2443354716],"iteration":775,"passed_time":144.6195181,"remaining_time":41.74584028},
{"learn":[0.2442188713],"iteration":776,"passed_time":144.7751665,"remaining_time":41.55065912},
{"learn":[0.2441318065],"iteration":777,"passed_time":144.9733235,"remaining_time":41.36770927},
{"learn":[0.2438796791],"iteration":778,"passed_time":145.1883932,"remaining_time":41.18951848},
{"learn":[0.2435101695],"iteration":779,"passed_time":145.3912736,"remaining_time":41.00779511},
{"learn":[0.2432174719],"iteration":780,"passed_time":145.5997049,"remaining_time":40.8275741},
{"learn":[0.2430024553],"iteration":781,"passed_time":145.8025468,"remaining_time":40.64572278},
{"learn":[0.2428227582],"iteration":782,"passed_time":146.0052694,"remaining_time":40.46378475},
{"learn":[0.2425279596],"iteration":783,"passed_time":146.1678635,"remaining_time":40.27073791},
{"learn":[0.2423431284],"iteration":784,"passed_time":146.3494177,"remaining_time":40.08296152},
{"learn":[0.2421609587],"iteration":785,"passed_time":146.5305059,"remaining_time":39.89507412},
{"learn":[0.2418425774],"iteration":786,"passed_time":146.7726605,"remaining_time":39.7237315},
{"learn":[0.241737763],"iteration":787,"passed_time":146.9992069,"remaining_time":39.54800997},
{"learn":[0.2415613375],"iteration":788,"passed_time":147.2264426,"remaining_time":39.37234397},
{"learn":[0.2413992574],"iteration":789,"passed_time":147.3941693,"remaining_time":39.18072855},
{"learn":[0.2411413967],"iteration":790,"passed_time":147.5483651,"remaining_time":38.98559836},
{"learn":[0.2408615083],"iteration":791,"passed_time":147.7478522,"remaining_time":38.80246622},
{"learn":[0.2407618597],"iteration":792,"passed_time":147.9536756,"remaining_time":38.62094685},
{"learn":[0.2405540565],"iteration":793,"passed_time":148.1437716,"remaining_time":38.43528582},
{"learn":[0.2403830139],"iteration":794,"passed_time":148.3329514,"remaining_time":38.2493774},
{"learn":[0.2402355517],"iteration":795,"passed_time":148.5382698,"remaining_time":38.06759677},
{"learn":[0.2401265599],"iteration":796,"passed_time":148.7115951,"remaining_time":37.87760829},
{"learn":[0.2399182392],"iteration":797,"passed_time":148.8783386,"remaining_time":37.68599548},
{"learn":[0.2396955576],"iteration":798,"passed_time":149.0546167,"remaining_time":37.49684349},
{"learn":[0.2395286016],"iteration":799,"passed_time":149.2412923,"remaining_time":37.31032307},
{"learn":[0.2392997856],"iteration":800,"passed_time":149.4267695,"remaining_time":37.12350452},
{"learn":[0.2390946002],"iteration":801,"passed_time":149.6046638,"remaining_time":36.93481724},
{"learn":[0.2388853466],"iteration":802,"passed_time":149.7968911,"remaining_time":36.74967316},
{"learn":[0.2386351616],"iteration":803,"passed_time":149.9911943,"remaining_time":36.56501752},
{"learn":[0.2382585465],"iteration":804,"passed_time":150.2164465,"remaining_time":36.38783486},
{"learn":[0.2379986221],"iteration":805,"passed_time":150.3675066,"remaining_time":36.19267528},
{"learn":[0.2379424829],"iteration":806,"passed_time":150.5622152,"remaining_time":36.00806386},
{"learn":[0.2377326803],"iteration":807,"passed_time":150.7514698,"remaining_time":35.82213144},
{"learn":[0.2375547874],"iteration":808,"passed_time":150.9679439,"remaining_time":35.64261717},
{"learn":[0.2373295211],"iteration":809,"passed_time":151.1414774,"remaining_time":35.45293915},
{"learn":[0.2370935213],"iteration":810,"passed_time":151.3454826,"remaining_time":35.27040223},
{"learn":[0.2369482049],"iteration":811,"passed_time":151.5177411,"remaining_time":35.08046222},
{"learn":[0.2367106066],"iteration":812,"passed_time":151.6771996,"remaining_time":34.88762157},
{"learn":[0.2364174651],"iteration":813,"passed_time":151.8420822,"remaining_time":34.69610231},
{"learn":[0.2362256122],"iteration":814,"passed_time":152.0548228,"remaining_time":34.51551193},
{"learn":[0.2360572401],"iteration":815,"passed_time":152.266536,"remaining_time":34.33461106},
{"learn":[0.235873779],"iteration":816,"passed_time":152.4524453,"remaining_time":34.14785495},
{"learn":[0.2356459643],"iteration":817,"passed_time":152.6293715,"remaining_time":33.95910222},
{"learn":[0.2355209524],"iteration":818,"passed_time":152.8337736,"remaining_time":33.77645058},
{"learn":[0.2353379764],"iteration":819,"passed_time":153.0333626,"remaining_time":33.59268935},
{"learn":[0.2350966647],"iteration":820,"passed_time":153.1825937,"remaining_time":33.3979102},
{"learn":[0.2349351489],"iteration":821,"passed_time":153.3380378,"remaining_time":33.20458727},
{"learn":[0.234631307],"iteration":822,"passed_time":153.5552103,"remaining_time":33.0246321},
{"learn":[0.2345180811],"iteration":823,"passed_time":153.7566074,"remaining_time":32.84121711},
{"learn":[0.2342719884],"iteration":824,"passed_time":153.9464185,"remaining_time":32.65530089},
{"learn":[0.2340020986],"iteration":825,"passed_time":154.145691,"remaining_time":32.47136833},
{"learn":[0.2338799566],"iteration":826,"passed_time":154.3686431,"remaining_time":32.29235218},
{"learn":[0.2337391656],"iteration":827,"passed_time":154.544305,"remaining_time":32.10340635},
{"learn":[0.2333593795],"iteration":828,"passed_time":154.752082,"remaining_time":31.92111703},
{"learn":[0.2332511595],"iteration":829,"passed_time":154.9288838,"remaining_time":31.73242199},
{"learn":[0.2328567742],"iteration":830,"passed_time":155.1269419,"remaining_time":31.54807844},
{"learn":[0.2326917873],"iteration":831,"passed_time":155.3258682,"remaining_time":31.36387722},
{"learn":[0.2325931769],"iteration":832,"passed_time":155.5316068,"remaining_time":31.18100641},
{"learn":[0.2323410271],"iteration":833,"passed_time":155.7224005,"remaining_time":30.99510609},
{"learn":[0.2321057744],"iteration":834,"passed_time":155.919248,"remaining_time":30.81039032},
{"learn":[0.231989782],"iteration":835,"passed_time":156.0566011,"remaining_time":30.61397439},
{"learn":[0.2318077642],"iteration":836,"passed_time":156.2525793,"remaining_time":30.42911639},
{"learn":[0.2315198703],"iteration":837,"passed_time":156.4432617,"remaining_time":30.24320811},
{"learn":[0.231295689],"iteration":838,"passed_time":156.6500181,"remaining_time":30.06037297},
{"learn":[0.2310096712],"iteration":839,"passed_time":156.8747504,"remaining_time":29.88090483},
{"learn":[0.230627451],"iteration":840,"passed_time":157.0848917,"remaining_time":29.69857048},
{"learn":[0.2304561145],"iteration":841,"passed_time":157.2890759,"remaining_time":29.51505225},
{"learn":[0.2302968983],"iteration":842,"passed_time":157.4247988,"remaining_time":29.31873477},
{"learn":[0.2300967206],"iteration":843,"passed_time":157.6176742,"remaining_time":29.13312461},
{"learn":[0.2298623233],"iteration":844,"passed_time":157.8212375,"remaining_time":28.94945776},
{"learn":[0.2297218246],"iteration":845,"passed_time":158.0138286,"remaining_time":28.76374657},
{"learn":[0.2295050654],"iteration":846,"passed_time":158.2101705,"remaining_time":28.57869668},
{"learn":[0.2293477906],"iteration":847,"passed_time":158.4203589,"remaining_time":28.39610206},
{"learn":[0.2291821819],"iteration":848,"passed_time":158.6155001,"remaining_time":28.21076621},
{"learn":[0.2290367609],"iteration":849,"passed_time":158.7551718,"remaining_time":28.01561855},
{"learn":[0.2288328669],"iteration":850,"passed_time":158.8854692,"remaining_time":27.81895994},
{"learn":[0.2287281572],"iteration":851,"passed_time":159.0968777,"remaining_time":27.63654684},
{"learn":[0.2285137317],"iteration":852,"passed_time":159.290806,"remaining_time":27.45105333},
{"learn":[0.2283893648],"iteration":853,"passed_time":159.487339,"remaining_time":27.26598535},
{"learn":[0.2281544636],"iteration":854,"passed_time":159.6727144,"remaining_time":27.07899835},
{"learn":[0.2279914939],"iteration":855,"passed_time":159.8750178,"remaining_time":26.8948628},
{"learn":[0.2277758824],"iteration":856,"passed_time":160.0510594,"remaining_time":26.70630279},
{"learn":[0.2274965707],"iteration":857,"passed_time":160.2195408,"remaining_time":26.51652073},
{"learn":[0.2272476554],"iteration":858,"passed_time":160.4223843,"remaining_time":26.33242862},
{"learn":[0.2271916743],"iteration":859,"passed_time":160.6114023,"remaining_time":26.14604223},
{"learn":[0.2270801271],"iteration":860,"passed_time":160.8096986,"remaining_time":25.96114763},
{"learn":[0.2267864489],"iteration":861,"passed_time":161.0114249,"remaining_time":25.77677103},
{"learn":[0.22661491],"iteration":862,"passed_time":161.1494206,"remaining_time":25.5822371},
{"learn":[0.2264809017],"iteration":863,"passed_time":161.3572739,"remaining_time":25.39883016},
{"learn":[0.2261702255],"iteration":864,"passed_time":161.5524684,"remaining_time":25.21339102},
{"learn":[0.2259877799],"iteration":865,"passed_time":161.6942065,"remaining_time":25.01965782},
{"learn":[0.2256540923],"iteration":866,"passed_time":161.9073828,"remaining_time":24.83700336},
{"learn":[0.2255575772],"iteration":867,"passed_time":162.1100764,"remaining_time":24.65268443},
{"learn":[0.225355143],"iteration":868,"passed_time":162.3132494,"remaining_time":24.46839548},
{"learn":[0.224979168],"iteration":869,"passed_time":162.5128742,"remaining_time":24.28353293},
{"learn":[0.2247399137],"iteration":870,"passed_time":162.7177346,"remaining_time":24.0994119},
{"learn":[0.2245937973],"iteration":871,"passed_time":162.921606,"remaining_time":23.91509813},
{"learn":[0.2243843319],"iteration":872,"passed_time":163.0719766,"remaining_time":23.72295651},
{"learn":[0.22419962],"iteration":873,"passed_time":163.2637319,"remaining_time":23.53687668},
{"learn":[0.2241182025],"iteration":874,"passed_time":163.4647844,"remaining_time":23.35211206},
{"learn":[0.2240305946],"iteration":875,"passed_time":163.6442359,"remaining_time":23.16425257},
{"learn":[0.2238410954],"iteration":876,"passed_time":163.8480393,"remaining_time":22.97982763},
{"learn":[0.2236719429],"iteration":877,"passed_time":164.046685,"remaining_time":22.79464188},
{"learn":[0.2234492988],"iteration":878,"passed_time":164.2669346,"remaining_time":22.61239941},
{"learn":[0.2233872749],"iteration":879,"passed_time":164.4245401,"remaining_time":22.4215282},
{"learn":[0.2231154123],"iteration":880,"passed_time":164.6009465,"remaining_time":22.233272},
{"learn":[0.2228616753],"iteration":881,"passed_time":164.8003681,"remaining_time":22.04812181},
{"learn":[0.2227496673],"iteration":882,"passed_time":165.0012468,"remaining_time":21.86313236},
{"learn":[0.222585311],"iteration":883,"passed_time":165.2057106,"remaining_time":21.67857741},
{"learn":[0.2223858066],"iteration":884,"passed_time":165.4192501,"remaining_time":21.4951568},
{"learn":[0.2220967066],"iteration":885,"passed_time":165.6259775,"remaining_time":21.31079169},
{"learn":[0.2219051071],"iteration":886,"passed_time":165.8184527,"remaining_time":21.12456049},
{"learn":[0.2216381653],"iteration":887,"passed_time":165.9587228,"remaining_time":20.9317308},
{"learn":[0.2215039301],"iteration":888,"passed_time":166.1900716,"remaining_time":20.75039139},
{"learn":[0.221316003],"iteration":889,"passed_time":166.4077072,"remaining_time":20.56724471},
{"learn":[0.221080841],"iteration":890,"passed_time":166.6102331,"remaining_time":20.38217218},
{"learn":[0.2209197211],"iteration":891,"passed_time":166.8085651,"remaining_time":20.19655272},
{"learn":[0.220739915],"iteration":892,"passed_time":167.0111434,"remaining_time":20.0114136},
{"learn":[0.22067554],"iteration":893,"passed_time":167.1922509,"remaining_time":19.82368971},
{"learn":[0.220441996],"iteration":894,"passed_time":167.3546265,"remaining_time":19.63378299},
{"learn":[0.2202761352],"iteration":895,"passed_time":167.5554053,"remaining_time":19.44839526},
{"learn":[0.2200640941],"iteration":896,"passed_time":167.7395699,"remaining_time":19.26106544},
{"learn":[0.2199041428],"iteration":897,"passed_time":167.9283758,"remaining_time":19.07426986},
{"learn":[0.2196293151],"iteration":898,"passed_time":168.1411667,"remaining_time":18.89016445},
{"learn":[0.2193847345],"iteration":899,"passed_time":168.3174854,"remaining_time":18.70194283},
{"learn":[0.2191922389],"iteration":900,"passed_time":168.5239275,"remaining_time":18.51705751},
{"learn":[0.2191179605],"iteration":901,"passed_time":168.6624472,"remaining_time":18.32474482},
{"learn":[0.2187378373],"iteration":902,"passed_time":168.8285217,"remaining_time":18.13551119},
{"learn":[0.2185176496],"iteration":903,"passed_time":169.035463,"remaining_time":17.95066863},
{"learn":[0.2180974928],"iteration":904,"passed_time":169.213637,"remaining_time":17.76275748},
{"learn":[0.2179047367],"iteration":905,"passed_time":169.42513,"remaining_time":17.57832475},
{"learn":[0.217735569],"iteration":906,"passed_time":169.6027762,"remaining_time":17.39036184},
{"learn":[0.2174763013],"iteration":907,"passed_time":169.8086525,"remaining_time":17.20528197},
{"learn":[0.2172422566],"iteration":908,"passed_time":170.0177961,"remaining_time":17.02048344},
{"learn":[0.2170724433],"iteration":909,"passed_time":170.1601075,"remaining_time":16.82902163},
{"learn":[0.2167936041],"iteration":910,"passed_time":170.3651849,"remaining_time":16.64379962},
{"learn":[0.2166077211],"iteration":911,"passed_time":170.5811781,"remaining_time":16.45958736},
{"learn":[0.2164956712],"iteration":912,"passed_time":170.8359346,"remaining_time":16.27899925},
{"learn":[0.216273174],"iteration":913,"passed_time":171.0396914,"remaining_time":16.09345018},
{"learn":[0.2162176507],"iteration":914,"passed_time":171.2288532,"remaining_time":15.90650548},
{"learn":[0.2160313442],"iteration":915,"passed_time":171.3699557,"remaining_time":15.71514877},
{"learn":[0.2158276555],"iteration":916,"passed_time":171.5367432,"remaining_time":15.52622649},
{"learn":[0.2156576564],"iteration":917,"passed_time":171.7279881,"remaining_time":15.33953706},
{"learn":[0.21545352],"iteration":918,"passed_time":171.9151407,"remaining_time":15.15247703},
{"learn":[0.215352751],"iteration":919,"passed_time":172.1105221,"remaining_time":14.96613236},
{"learn":[0.215231205],"iteration":920,"passed_time":172.3174685,"remaining_time":14.78076006},
{"learn":[0.2149871943],"iteration":921,"passed_time":172.5242293,"remaining_time":14.59532526},
{"learn":[0.2147293023],"iteration":922,"passed_time":172.715281,"remaining_time":14.40853373},
{"learn":[0.2145214657],"iteration":923,"passed_time":172.9049381,"remaining_time":14.22161828},
{"learn":[0.2142562957],"iteration":924,"passed_time":173.0468106,"remaining_time":14.03082248},
{"learn":[0.2139489885],"iteration":925,"passed_time":173.2260334,"remaining_time":13.84311714},
{"learn":[0.2136917096],"iteration":926,"passed_time":173.4298133,"remaining_time":13.65736394},
{"learn":[0.213484195],"iteration":927,"passed_time":173.6259207,"remaining_time":13.47097661},
{"learn":[0.2133506651],"iteration":928,"passed_time":173.82191,"remaining_time":13.28455932},
{"learn":[0.2131065874],"iteration":929,"passed_time":173.9805357,"remaining_time":13.09530914},
{"learn":[0.2129588935],"iteration":930,"passed_time":174.1866527,"remaining_time":12.90964451},
{"learn":[0.2128119419],"iteration":931,"passed_time":174.3752384,"remaining_time":12.72265688},
{"learn":[0.2126781505],"iteration":932,"passed_time":174.5251047,"remaining_time":12.53288534},
{"learn":[0.2125825699],"iteration":933,"passed_time":174.6895579,"remaining_time":12.34423},
{"learn":[0.2123931864],"iteration":934,"passed_time":174.878202,"remaining_time":12.15730816},
{"learn":[0.2122573655],"iteration":935,"passed_time":175.0636165,"remaining_time":11.97016181},
{"learn":[0.2121246133],"iteration":936,"passed_time":175.2355817,"remaining_time":11.78211488},
{"learn":[0.2119610573],"iteration":937,"passed_time":175.4276104,"remaining_time":11.59542841},
{"learn":[0.2117660697],"iteration":938,"passed_time":175.6481035,"remaining_time":11.41057967},
{"learn":[0.2115715404],"iteration":939,"passed_time":175.807066,"remaining_time":11.22172762},
{"learn":[0.2113603902],"iteration":940,"passed_time":175.9944667,"remaining_time":11.03472214},
{"learn":[0.2112826011],"iteration":941,"passed_time":176.1955978,"remaining_time":10.84856122},
{"learn":[0.211049773],"iteration":942,"passed_time":176.4061917,"remaining_time":10.66294054},
{"learn":[0.2109340849],"iteration":943,"passed_time":176.5995465,"remaining_time":10.47624429},
{"learn":[0.2108241861],"iteration":944,"passed_time":176.8129139,"remaining_time":10.29069869},
{"learn":[0.2107533348],"iteration":945,"passed_time":177.0234745,"remaining_time":10.10493406},
{"learn":[0.21064766],"iteration":946,"passed_time":177.2358406,"remaining_time":9.91921811},
{"learn":[0.2105282208],"iteration":947,"passed_time":177.4374533,"remaining_time":9.732856087},
{"learn":[0.2104705569],"iteration":948,"passed_time":177.6376771,"remaining_time":9.546387286},
{"learn":[0.2102802428],"iteration":949,"passed_time":177.8461045,"remaining_time":9.36032129},
{"learn":[0.2100045111],"iteration":950,"passed_time":178.0696599,"remaining_time":9.174987734},
{"learn":[0.2098548812],"iteration":951,"passed_time":178.2750183,"remaining_time":8.988656386},
{"learn":[0.2095665597],"iteration":952,"passed_time":178.4903648,"remaining_time":8.802777699},
{"learn":[0.209381044],"iteration":953,"passed_time":178.6402121,"remaining_time":8.613678993},
{"learn":[0.2091468983],"iteration":954,"passed_time":178.8108361,"remaining_time":8.425641492},
{"learn":[0.209092355],"iteration":955,"passed_time":178.9841873,"remaining_time":8.237765944},
{"learn":[0.2089556433],"iteration":956,"passed_time":179.1694852,"remaining_time":8.05045754},
{"learn":[0.208799581],"iteration":957,"passed_time":179.372317,"remaining_time":7.863922039},
{"learn":[0.2086296423],"iteration":958,"passed_time":179.5334708,"remaining_time":7.675570701},
{"learn":[0.2083932522],"iteration":959,"passed_time":179.7346128,"remaining_time":7.4889422},
{"learn":[0.2082834225],"iteration":960,"passed_time":179.9479085,"remaining_time":7.302776725},
{"learn":[0.2081464493],"iteration":961,"passed_time":180.1371268,"remaining_time":7.115603761},
{"learn":[0.2079693028],"iteration":962,"passed_time":180.3106605,"remaining_time":6.927823923},
{"learn":[0.207833901],"iteration":963,"passed_time":180.5202437,"remaining_time":6.74141989},
{"learn":[0.2076562794],"iteration":964,"passed_time":180.7342077,"remaining_time":6.555126704},
{"learn":[0.2074749846],"iteration":965,"passed_time":180.966592,"remaining_time":6.369424563},
{"learn":[0.2072497367],"iteration":966,"passed_time":181.1397009,"remaining_time":6.181603029},
{"learn":[0.207042285],"iteration":967,"passed_time":181.3477852,"remaining_time":5.994968107},
{"learn":[0.2068932193],"iteration":968,"passed_time":181.498697,"remaining_time":5.806459863},
{"learn":[0.2067579471],"iteration":969,"passed_time":181.6259695,"remaining_time":5.617298025},
{"learn":[0.2066453776],"iteration":970,"passed_time":181.791184,"remaining_time":5.429396845},
{"learn":[0.2065009687],"iteration":971,"passed_time":181.9754406,"remaining_time":5.242090881},
{"learn":[0.2064000312],"iteration":972,"passed_time":182.196691,"remaining_time":5.055817735},
{"learn":[0.2061633479],"iteration":973,"passed_time":182.3994549,"remaining_time":4.868979288},
{"learn":[0.2058293633],"iteration":974,"passed_time":182.5962346,"remaining_time":4.681954734},
{"learn":[0.2057869517],"iteration":975,"passed_time":182.8035206,"remaining_time":4.49516854},
{"learn":[0.2055699472],"iteration":976,"passed_time":182.9376955,"remaining_time":4.306619238},
{"learn":[0.2053177796],"iteration":977,"passed_time":183.0979147,"remaining_time":4.118766997},
{"learn":[0.2051579451],"iteration":978,"passed_time":183.2977476,"remaining_time":3.931820939},
{"learn":[0.2049595879],"iteration":979,"passed_time":183.5020315,"remaining_time":3.744939418},
{"learn":[0.2048693279],"iteration":980,"passed_time":183.7135575,"remaining_time":3.558162683},
{"learn":[0.2047804937],"iteration":981,"passed_time":183.9116441,"remaining_time":3.371089199},
{"learn":[0.2047106289],"iteration":982,"passed_time":184.1251827,"remaining_time":3.184260534},
{"learn":[0.2045831189],"iteration":983,"passed_time":184.328638,"remaining_time":2.997213626},
{"learn":[0.2043261325],"iteration":984,"passed_time":184.4819729,"remaining_time":2.809370146},
{"learn":[0.2041784121],"iteration":985,"passed_time":184.6798227,"remaining_time":2.62222872},
{"learn":[0.2038989886],"iteration":986,"passed_time":184.8982254,"remaining_time":2.435336302},
{"learn":[0.2035708343],"iteration":987,"passed_time":185.0961585,"remaining_time":2.24813148},
{"learn":[0.2034415509],"iteration":988,"passed_time":185.2858321,"remaining_time":2.060813097},
{"learn":[0.2031671623],"iteration":989,"passed_time":185.4785172,"remaining_time":1.873520376},
{"learn":[0.2030939809],"iteration":990,"passed_time":185.6801942,"remaining_time":1.686298433},
{"learn":[0.202986867],"iteration":991,"passed_time":185.8286356,"remaining_time":1.498618029},
{"learn":[0.2027488557],"iteration":992,"passed_time":186.0101374,"remaining_time":1.31124971},
{"learn":[0.2026655515],"iteration":993,"passed_time":186.1977135,"remaining_time":1.12392986},
{"learn":[0.2024930868],"iteration":994,"passed_time":186.4098844,"remaining_time":0.9367330876},
{"learn":[0.2023666569],"iteration":995,"passed_time":186.5948239,"remaining_time":0.7493768027},
{"learn":[0.2022688855],"iteration":996,"passed_time":186.8009589,"remaining_time":0.5620891442},
{"learn":[0.2021218086],"iteration":997,"passed_time":186.9950212,"remaining_time":0.3747395214},
{"learn":[0.201979079],"iteration":998,"passed_time":187.2116668,"remaining_time":0.1873990659},
{"learn":[0.2017983995],"iteration":999,"passed_time":187.384646,"remaining_time":0}
]}